Workbook

Sheet Cover
B2: Value-Based Primary Care — Capitation Financial Model
B3: Greenbrook-scale · ~$60M revenue · 4 clinics · ~4,500 members · 4 MA / Medicare payors
B5: PURPOSE
B6: Demonstrates how a senior-focused primary care clinic earns and bears risk across four
B7: different value-based contract structures simultaneously, and how the two core profit
B8: levers — RISK SCORE (RAF) capture and TOTAL COST OF CARE (TCOC) management — drive
B9: the medical margin and the cohort J-curve as a panel matures.
B11: THE FOUR CONTRACTS
B12: A · Full / Global Capitation
B13: 100% TCOC risk. Revenue = % of risk-adjusted premium. Provider pays claims; keeps surplus, bears deficit. Stop-loss protection.
B14: B · Two-Sided Shared Risk
B15: Care-management PMPM + 50/50 share of savings/losses vs a TCOC target. Plan pays claims; provider settles the shared portion.
... B21: TABS
B22: Assumptions | C22: All inputs & levers (blue). Edit here to flex scenarios.
B23: A·FullCap / B·TwoSided / C·Upside / D·REACH | C23: Per-contract monthly economics (Year 1).
B24: P&L (Monthly) | C24: Consolidated Year-1 monthly P&L to EBITDA.
B25: Cash Flow | C25: Full-cap cash dynamics: cap received vs claims paid in arrears + IBNR build.
B26: 3-Yr & Cohorts | C26: Annual summary + cohort J-curve showing RAF & TCOC levers maturing.
B27: KPIs | C27: Dashboard: MLR, medical margin PMPM, utilization by contract.
B30: COLOR KEY
B31: Blue = input/assumption | C31: Black = formula | D31: Green = cross-sheet link
B33: Illustrative model. Assumptions are synthetic and directional, not Greenbrook actuals.

Sheet Assumptions
A1: ASSUMPTIONS & LEVERS
A3: GLOBAL
A4: Model start year | B4: 2026
A5: Annual medical cost trend | B5: 0.05
A6: Annual premium / benchmark trend | B6: 0.035
A7: IBNR accrual (% of monthly medical cost) | B7: 0.12
A8: Claims payment lag (months) | B8: 2
A9: New-clinic TCOC factor — Month 1 | B9: 1.06
A10: New-clinic TCOC factor — Month 12 | B10: 1
A11: Inpatient admits / 1,000 (mature) | B11: 185
A13: CLINIC OPERATING COSTS
A14: Fixed clinic opex / month ($) | B14: 380000
A15: Care management — variable PMPM ($) | B15: 18
A16: G&A / corporate / month ($) | B16: 120000
A18: TCOC BUCKET MIX (% of total medical spend)
A19: Inpatient | B19: 0.3
A20: Outpatient / ED | B20: 0.16
A21: Specialist professional | B21: 0.18
A22: Primary care (internal) | B22: 0.08
A23: Post-acute / SNF | B23: 0.1
A24: Pharmacy (Part D) | B24: 0.12
A25: Ancillary (lab / imaging / DME) | B25: 0.04
A26: Other | B26: 0.02
A27: Total | B27: =SUM(B19:B26) -> 1
A29: CONTRACT TERMS
A30: Metric | B30: A · Full Cap | C30: B · Two-Sided | D30: C · Upside-Only | E30: D · ACO REACH
A31: Population / payor | B31: MA — Payor A | C31: MA — Payor B | D31: MA — Payor C | E31: Traditional Medicare
A32: Risk model | B32: Full global cap | C32: Two-sided shared | D32: Upside-only | E32: REACH Professional
A33: Full-cap flag (1=yes) | B33: 1 | C33: 0 | D33: 0 | E33: 0
A34: Starting members (Month 1) | B34: 3600 | C34: 450 | D34: 250 | E34: 200
A35: Monthly member growth | B35: 0.01 | C35: 0.01 | D35: 0.01 | E35: 0.015
A36: Mature RAF (risk score) | B36: 1.12 | C36: 1.05 | D36: 1 | E36: 1.05
A37: Premium / benchmark PMPM ($) | B37: 1450 | C37: 1350 | D37: 1250 | E37: 1150
A38: Provider cap % of premium | B38: 0.9 | C38: 0 | D38: 0 | E38: 0
A39: Care management PMPM ($) | B39: 0 | C39: 55 | D39: 0 | E39: 0
A40: Primary care cap PMPM ($) | B40: 0 | C40: 0 | D40: 0 | E40: 80
A41: FFS own-services PMPM ($) | B41: 0 | C41: 0 | D41: 50 | E41: 0
A42: TCOC target / benchmark (% of prem) | B42: 0 | C42: 0.88 | D42: 0.9 | E42: 0.98
A43: Provider savings split | B43: 0 | C43: 0.5 | D43: 0.6 | E43: 0.5
A44: Provider loss split | B44: 0 | C44: 0.5 | D44: 0 | E44: 0.5
... A48: Stop-loss recoveries PMPM ($) | B48: 26 | C48: 0 | D48: 0 | E48: 0
A50: COHORT / J-CURVE (by member tenure)
A51: Tenure | B51: RAF factor (× mature) | C51: TCOC factor (× mature)
A52: Year 1 (new) | B52: 0.9 | C52: 1.06
A53: Year 2 | B53: 0.98 | C53: 1.02
A54: Year 3+ (mature) | B54: 1 | C54: 1
A56: MULTI-YEAR ENROLLMENT (clinic cohorts)
B57: Year 1 | C57: Year 2 | D57: Year 3
A58: New members enrolled (cohort) | B58: 4500 | C58: 900 | D58: 800
A59: Annual retention | B59: 0.9 | C59: 0.9 | D59: 0.9

Sheet A. Full Cap
A1: CONTRACT A — Full / Global Capitation (100% TCOC risk)
A2: ($ unless noted) | C2: Jan | D2: Feb | E2: Mar | F2: Apr | G2: May | H2: Jun | I2: Jul | J2: Aug | K2: Sep | L2: Oct | M2: Nov | N2: Dec | O2: Year 1
A3: MEMBERSHIP
A4: Members — beginning | C4: =Assumptions!$B$34 -> 3600 | D4: =C5 -> 3636 | E4: =D5 -> 3672.36 | F4: =E5 -> 3709.0836 | G4: =F5 -> 3746.1744 | H4: =G5 -> 3783.6362 | I4: =H5 -> 3821.4725 | J4: =I5 -> 3859.6873 | K4: =J5 -> 3898.2841 | ... N4: =M5 -> 4016.406
A5: Members — ending | C5: =C4*(1+Assumptions!$B$35) -> 3636 | D5: =D4*(1+Assumptions!$B$35) -> 3672.36 | E5: =E4*(1+Assumptions!$B$35) -> 3709.0836 | F5: =F4*(1+Assumptions!$B$35) -> 3746.1744 | G5: =G4*(1+Assumptions!$B$35) -> 3783.6362 | H5: =H4*(1+Assumptions!$B$35) -> 3821.4725 | I5: =I4*(1+Assumptions!$B$35) -> 3859.6873 | J5: =J4*(1+Assumptions!$B$35) -> 3898.2841 | ... N5: =N4*(1+Assumptions!$B$35) -> 4056.5701 | O5: =N5 -> 4056.5701
A6: Member-months (avg) | C6: =AVERAGE(C4,C5) -> 3618 | D6: =AVERAGE(D4,D5) -> 3654.18 | E6: =AVERAGE(E4,E5) -> 3690.7218 | F6: =AVERAGE(F4,F5) -> 3727.629 | G6: =AVERAGE(G4,G5) -> 3764.9053 | H6: =AVERAGE(H4,H5) -> 3802.5544 | I6: =AVERAGE(I4,I5) -> 3840.5799 | J6: =AVERAGE(J4,J5) -> 3878.9857 | ... N6: =AVERAGE(N4,N5) -> 4036.4881 | O6: =SUM(C6:N6) -> 45885.296
A8: LEVERS — RISK & TCOC
A9: RAF (risk score, Yr-1 cohort) | C9: =Assumptions!$B$36*Assumptions!$B$52 -> 1.008 | D9: =Assumptions!$B$36*Assumptions!$B$52 -> 1.008 | E9: =Assumptions!$B$36*Assumptions!$B$52 -> 1.008 | F9: =Assumptions!$B$36*Assumptions!$B$52 -> 1.008 | G9: =Assumptions!$B$36*Assumptions!$B$52 -> 1.008 | H9: =Assumptions!$B$36*Assumptions!$B$52 -> 1.008 | I9: =Assumptions!$B$36*Assumptions!$B$52 -> 1.008 | J9: =Assumptions!$B$36*Assumptions!$B$52 -> 1.008 | ... N9: =Assumptions!$B$36*Assumptions!$B$52 -> 1.008
A10: Premium / benchmark PMPM | C10: =Assumptions!$B$37 -> 1450 | D10: =Assumptions!$B$37 -> 1450 | E10: =Assumptions!$B$37 -> 1450 | F10: =Assumptions!$B$37 -> 1450 | G10: =Assumptions!$B$37 -> 1450 | H10: =Assumptions!$B$37 -> 1450 | I10: =Assumptions!$B$37 -> 1450 | J10: =Assumptions!$B$37 -> 1450 | ... N10: =Assumptions!$B$37 -> 1450
A11: New-clinic TCOC factor | C11: =Assumptions!$B$9+(Assumptions!$B$10-Assumptions!$B$9)*(0)/11 -> 1.06 | D11: =Assumptions!$B$9+(Assumptions!$B$10-Assumptions!$B$9)*(1)/11 -> 1.0545455 | E11: =Assumptions!$B$9+(Assumptions!$B$10-Assumptions!$B$9)*(2)/11 -> 1.0490909 | F11: =Assumptions!$B$9+(Assumptions!$B$10-Assumptions!$B$9)*(3)/11 -> 1.0436364 | G11: =Assumptions!$B$9+(Assumptions!$B$10-Assumptions!$B$9)*(4)/11 -> 1.0381818 | H11: =Assumptions!$B$9+(Assumptions!$B$10-Assumptions!$B$9)*(5)/11 -> 1.0327273 | I11: =Assumptions!$B$9+(Assumptions!$B$10-Assumptions!$B$9)*(6)/11 -> 1.0272727 | J11: =Assumptions!$B$9+(Assumptions!$B$10-Assumptions!$B$9)*(7)/11 -> 1.0218182 | K11: =Assumptions!$B$9+(Assumptions!$B$10-Assumptions!$B$9)*(8)/11 -> 1.0163636 | L11: =Assumptions!$B$9+(Assumptions!$B$10-Assumptions!$B$9)*(9)/11 -> 1.0109091 | M11: =Assumptions!$B$9+(Assumptions!$B$10-Assumptions!$B$9)*(10)/11 -> 1.0054545 | N11: =Assumptions!$B$9+(Assumptions!$B$10-Assumptions!$B$9)*(11)/11 -> 1
A12: Actual TCOC PMPM | C12: =Assumptions!$B$46*C11 -> 1208.4 | D12: =Assumptions!$B$46*D11 -> 1202.1818 | E12: =Assumptions!$B$46*E11 -> 1195.9636 | F12: =Assumptions!$B$46*F11 -> 1189.7455 | G12: =Assumptions!$B$46*G11 -> 1183.5273 | H12: =Assumptions!$B$46*H11 -> 1177.3091 | I12: =Assumptions!$B$46*I11 -> 1171.0909 | J12: =Assumptions!$B$46*J11 -> 1164.8727 | ... N12: =Assumptions!$B$46*N11 -> 1140
A14: REVENUE
A15: Global capitation | C15: =C6*C10*C9*Assumptions!$B$38 -> 4759261.9 | D15: =D6*D10*D9*Assumptions!$B$38 -> 4806854.5 | E15: =E6*E10*E9*Assumptions!$B$38 -> 4854923.1 | F15: =F6*F10*F9*Assumptions!$B$38 -> 4903472.3 | G15: =G6*G10*G9*Assumptions!$B$38 -> 4952507 | H15: =H6*H10*H9*Assumptions!$B$38 -> 5002032.1 | I15: =I6*I10*I9*Assumptions!$B$38 -> 5052052.4 | J15: =J6*J10*J9*Assumptions!$B$38 -> 5102573 | ... N15: =N6*N10*N9*Assumptions!$B$38 -> 5309757.9 | O15: =SUM(C15:N15) -> 60359354
A16: Care management | C16: =C6*Assumptions!$B$39 -> 0 | D16: =D6*Assumptions!$B$39 -> 0 | E16: =E6*Assumptions!$B$39 -> 0 | F16: =F6*Assumptions!$B$39 -> 0 | G16: =G6*Assumptions!$B$39 -> 0 | H16: =H6*Assumptions!$B$39 -> 0 | I16: =I6*Assumptions!$B$39 -> 0 | J16: =J6*Assumptions!$B$39 -> 0 | ... N16: =N6*Assumptions!$B$39 -> 0 | O16: =SUM(C16:N16) -> 0
A17: Primary care cap (PCCP) | C17: =C6*Assumptions!$B$40 -> 0 | D17: =D6*Assumptions!$B$40 -> 0 | E17: =E6*Assumptions!$B$40 -> 0 | F17: =F6*Assumptions!$B$40 -> 0 | G17: =G6*Assumptions!$B$40 -> 0 | H17: =H6*Assumptions!$B$40 -> 0 | I17: =I6*Assumptions!$B$40 -> 0 | J17: =J6*Assumptions!$B$40 -> 0 | ... N17: =N6*Assumptions!$B$40 -> 0 | O17: =SUM(C17:N17) -> 0
A18: FFS own services | C18: =C6*Assumptions!$B$41 -> 0 | D18: =D6*Assumptions!$B$41 -> 0 | E18: =E6*Assumptions!$B$41 -> 0 | F18: =F6*Assumptions!$B$41 -> 0 | G18: =G6*Assumptions!$B$41 -> 0 | H18: =H6*Assumptions!$B$41 -> 0 | I18: =I6*Assumptions!$B$41 -> 0 | J18: =J6*Assumptions!$B$41 -> 0 | ... N18: =N6*Assumptions!$B$41 -> 0 | O18: =SUM(C18:N18) -> 0
A19: Benchmark / target TCOC (memo) | C19: =C6*C10*C9*Assumptions!$B$42 -> 0 | D19: =D6*D10*D9*Assumptions!$B$42 -> 0 | E19: =E6*E10*E9*Assumptions!$B$42 -> 0 | F19: =F6*F10*F9*Assumptions!$B$42 -> 0 | G19: =G6*G10*G9*Assumptions!$B$42 -> 0 | H19: =H6*H10*H9*Assumptions!$B$42 -> 0 | I19: =I6*I10*I9*Assumptions!$B$42 -> 0 | J19: =J6*J10*J9*Assumptions!$B$42 -> 0 | ... N19: =N6*N10*N9*Assumptions!$B$42 -> 0 | O19: =SUM(C19:N19) -> 0
A20: Actual TCOC (memo) | C20: =C6*C12 -> 4371991.2 | D20: =D6*D12 -> 4392988.8 | E20: =E6*E12 -> 4413969.1 | F20: =F6*F12 -> 4434929.7 | G20: =G6*G12 -> 4455868.1 | H20: =H6*H12 -> 4476781.8 | I20: =I6*I12 -> 4497668.2 | J20: =J6*J12 -> 4518524.7 | ... N20: =N6*N12 -> 4601596.4 | O20: =SUM(C20:N20) -> 53844690
A21: Gross savings vs benchmark (memo) | C21: =C19-C20 -> -4371991.2 | D21: =D19-D20 -> -4392988.8 | E21: =E19-E20 -> -4413969.1 | F21: =F19-F20 -> -4434929.7 | G21: =G19-G20 -> -4455868.1 | H21: =H19-H20 -> -4476781.8 | I21: =I19-I20 -> -4497668.2 | J21: =J19-J20 -> -4518524.7 | ... N21: =N19-N20 -> -4601596.4 | O21: =SUM(C21:N21) -> -53844690
A22: Shared savings / (loss) settlement | C22: =IF(Assumptions!$B$33=1,0,IF(C21>=0,C21*Assumptions!$B$43,C21*Assumptions!$B$44*Assumptions!$B$45)) -> 0 | D22: =IF(Assumptions!$B$33=1,0,IF(D21>=0,D21*Assumptions!$B$43,D21*Assumptions!$B$44*Assumptions!$B$45)) -> 0 | E22: =IF(Assumptions!$B$33=1,0,IF(E21>=0,E21*Assumptions!$B$43,E21*Assumptions!$B$44*Assumptions!$B$45)) -> 0 | F22: =IF(Assumptions!$B$33=1,0,IF(F21>=0,F21*Assumptions!$B$43,F21*Assumptions!$B$44*Assumptions!$B$45)) -> 0 | G22: =IF(Assumptions!$B$33=1,0,IF(G21>=0,G21*Assumptions!$B$43,G21*Assumptions!$B$44*Assumptions!$B$45)) -> 0 | H22: =IF(Assumptions!$B$33=1,0,IF(H21>=0,H21*Assumptions!$B$43,H21*Assumptions!$B$44*Assumptions!$B$45)) -> 0 | I22: =IF(Assumptions!$B$33=1,0,IF(I21>=0,I21*Assumptions!$B$43,I21*Assumptions!$B$44*Assumptions!$B$45)) -> 0 | J22: =IF(Assumptions!$B$33=1,0,IF(J21>=0,J21*Assumptions!$B$43,J21*Assumptions!$B$44*Assumptions!$B$45)) -> 0 | ... N22: =IF(Assumptions!$B$33=1,0,IF(N21>=0,N21*Assumptions!$B$43,N21*Assumptions!$B$44*Assumptions!$B$45)) -> 0 | O22: =SUM(C22:N22) -> 0
A23: TOTAL PROVIDER REVENUE | C23: =C15+C16+C17+C18+C22 -> 4759261.9 | D23: =D15+D16+D17+D18+D22 -> 4806854.5 | E23: =E15+E16+E17+E18+E22 -> 4854923.1 | F23: =F15+F16+F17+F18+F22 -> 4903472.3 | G23: =G15+G16+G17+G18+G22 -> 4952507 | H23: =H15+H16+H17+H18+H22 -> 5002032.1 | I23: =I15+I16+I17+I18+I22 -> 5052052.4 | J23: =J15+J16+J17+J18+J22 -> 5102573 | ... N23: =N15+N16+N17+N18+N22 -> 5309757.9 | O23: =SUM(C23:N23) -> 60359354
A25: PROVIDER MEDICAL COST (cash-bearing)
A26: Medical claims (full-cap only) | C26: =Assumptions!$B$33*C20 -> 4371991.2 | D26: =Assumptions!$B$33*D20 -> 4392988.8 | E26: =Assumptions!$B$33*E20 -> 4413969.1 | F26: =Assumptions!$B$33*F20 -> 4434929.7 | G26: =Assumptions!$B$33*G20 -> 4455868.1 | H26: =Assumptions!$B$33*H20 -> 4476781.8 | I26: =Assumptions!$B$33*I20 -> 4497668.2 | J26: =Assumptions!$B$33*J20 -> 4518524.7 | ... N26: =Assumptions!$B$33*N20 -> 4601596.4 | O26: =SUM(C26:N26) -> 53844690
A27: Stop-loss premium | C27: =Assumptions!$B$33*C6*Assumptions!$B$47 -> 126630 | D27: =Assumptions!$B$33*D6*Assumptions!$B$47 -> 127896.3 | E27: =Assumptions!$B$33*E6*Assumptions!$B$47 -> 129175.26 | F27: =Assumptions!$B$33*F6*Assumptions!$B$47 -> 130467.02 | G27: =Assumptions!$B$33*G6*Assumptions!$B$47 -> 131771.69 | H27: =Assumptions!$B$33*H6*Assumptions!$B$47 -> 133089.4 | I27: =Assumptions!$B$33*I6*Assumptions!$B$47 -> 134420.3 | J27: =Assumptions!$B$33*J6*Assumptions!$B$47 -> 135764.5 | ... N27: =Assumptions!$B$33*N6*Assumptions!$B$47 -> 141277.08 | O27: =SUM(C27:N27) -> 1605985.4
A28: Stop-loss recoveries | C28: =-Assumptions!$B$33*C6*Assumptions!$B$48 -> -94068 | D28: =-Assumptions!$B$33*D6*Assumptions!$B$48 -> -95008.68 | E28: =-Assumptions!$B$33*E6*Assumptions!$B$48 -> -95958.767 | F28: =-Assumptions!$B$33*F6*Assumptions!$B$48 -> -96918.354 | G28: =-Assumptions!$B$33*G6*Assumptions!$B$48 -> -97887.538 | H28: =-Assumptions!$B$33*H6*Assumptions!$B$48 -> -98866.413 | I28: =-Assumptions!$B$33*I6*Assumptions!$B$48 -> -99855.078 | J28: =-Assumptions!$B$33*J6*Assumptions!$B$48 -> -100853.63 | ... N28: =-Assumptions!$B$33*N6*Assumptions!$B$48 -> -104948.69 | O28: =SUM(C28:N28) -> -1193017.7
A29: TOTAL PROVIDER MEDICAL COST | C29: =C26+C27+C28 -> 4404553.2 | D29: =D26+D27+D28 -> 4425876.4 | E29: =E26+E27+E28 -> 4447185.6 | F29: =F26+F27+F28 -> 4468478.3 | G29: =G26+G27+G28 -> 4489752.3 | H29: =H26+H27+H28 -> 4511004.8 | I29: =I26+I27+I28 -> 4532233.4 | J29: =J26+J27+J28 -> 4553435.5 | ... N29: =N26+N27+N28 -> 4637924.8 | O29: =SUM(C29:N29) -> 54257658
A31: CONTRIBUTION & RATIOS
A32: Contribution margin | C32: =C23-C29 -> 354708.72 | D32: =D23-D29 -> 380978.16 | E32: =E23-E29 -> 407737.52 | F32: =F23-F29 -> 434993.97 | G32: =G23-G29 -> 462754.78 | H32: =H23-H29 -> 491027.3 | I32: =I23-I29 -> 519819 | J32: =J23-J29 -> 549137.43 | ... N32: =N23-N29 -> 671833.08 | O32: =SUM(C32:N32) -> 6101695.6
A33: Medical loss ratio (TCOC / premium) | C33: =IF(C6=0,0,C20/(C6*C10*C9)) -> 0.82676519 | D33: =IF(D6=0,0,D20/(D6*D10*D9)) -> 0.82251082 | E33: =IF(E6=0,0,E20/(E6*E10*E9)) -> 0.81825646 | F33: =IF(F6=0,0,F20/(F6*F10*F9)) -> 0.81400209 | G33: =IF(G6=0,0,G20/(G6*G10*G9)) -> 0.80974772 | H33: =IF(H6=0,0,H20/(H6*H10*H9)) -> 0.80549336 | I33: =IF(I6=0,0,I20/(I6*I10*I9)) -> 0.80123899 | J33: =IF(J6=0,0,J20/(J6*J10*J9)) -> 0.79698462 | ... N33: =IF(N6=0,0,N20/(N6*N10*N9)) -> 0.77996716 | O33: =O20/SUMPRODUCT(C6:N6,C10:N10,C9:N9) -> 0.80286183
A34: Contribution PMPM | C34: =IF(C6=0,0,C32/C6) -> 98.04 | D34: =IF(D6=0,0,D32/D6) -> 104.25818 | E34: =IF(E6=0,0,E32/E6) -> 110.47636 | F34: =IF(F6=0,0,F32/F6) -> 116.69455 | G34: =IF(G6=0,0,G32/G6) -> 122.91273 | H34: =IF(H6=0,0,H32/H6) -> 129.13091 | I34: =IF(I6=0,0,I32/I6) -> 135.34909 | J34: =IF(J6=0,0,J32/J6) -> 141.56727 | ... N34: =IF(N6=0,0,N32/N6) -> 166.44 | O34: =O32/O6 -> 132.97714

Sheet B. Two-Sided
A1: CONTRACT B — Two-Sided Shared Risk (50/50 vs target)
A2: ($ unless noted) | C2: Jan | D2: Feb | E2: Mar | F2: Apr | G2: May | H2: Jun | I2: Jul | J2: Aug | K2: Sep | L2: Oct | M2: Nov | N2: Dec | O2: Year 1
A3: MEMBERSHIP
A4: Members — beginning | C4: =Assumptions!$C$34 -> 450 | D4: =C5 -> 454.5 | E4: =D5 -> 459.045 | F4: =E5 -> 463.63545 | G4: =F5 -> 468.2718 | H4: =G5 -> 472.95452 | I4: =H5 -> 477.68407 | J4: =I5 -> 482.46091 | K4: =J5 -> 487.28552 | ... N4: =M5 -> 502.05076
A5: Members — ending | C5: =C4*(1+Assumptions!$C$35) -> 454.5 | D5: =D4*(1+Assumptions!$C$35) -> 459.045 | E5: =E4*(1+Assumptions!$C$35) -> 463.63545 | F5: =F4*(1+Assumptions!$C$35) -> 468.2718 | G5: =G4*(1+Assumptions!$C$35) -> 472.95452 | H5: =H4*(1+Assumptions!$C$35) -> 477.68407 | I5: =I4*(1+Assumptions!$C$35) -> 482.46091 | J5: =J4*(1+Assumptions!$C$35) -> 487.28552 | ... N5: =N4*(1+Assumptions!$C$35) -> 507.07126 | O5: =N5 -> 507.07126
A6: Member-months (avg) | C6: =AVERAGE(C4,C5) -> 452.25 | D6: =AVERAGE(D4,D5) -> 456.7725 | E6: =AVERAGE(E4,E5) -> 461.34022 | F6: =AVERAGE(F4,F5) -> 465.95363 | G6: =AVERAGE(G4,G5) -> 470.61316 | H6: =AVERAGE(H4,H5) -> 475.3193 | I6: =AVERAGE(I4,I5) -> 480.07249 | J6: =AVERAGE(J4,J5) -> 484.87321 | ... N6: =AVERAGE(N4,N5) -> 504.56101 | O6: =SUM(C6:N6) -> 5735.662
A8: LEVERS — RISK & TCOC
A9: RAF (risk score, Yr-1 cohort) | C9: =Assumptions!$C$36*Assumptions!$B$52 -> 0.945 | D9: =Assumptions!$C$36*Assumptions!$B$52 -> 0.945 | E9: =Assumptions!$C$36*Assumptions!$B$52 -> 0.945 | F9: =Assumptions!$C$36*Assumptions!$B$52 -> 0.945 | G9: =Assumptions!$C$36*Assumptions!$B$52 -> 0.945 | H9: =Assumptions!$C$36*Assumptions!$B$52 -> 0.945 | I9: =Assumptions!$C$36*Assumptions!$B$52 -> 0.945 | J9: =Assumptions!$C$36*Assumptions!$B$52 -> 0.945 | ... N9: =Assumptions!$C$36*Assumptions!$B$52 -> 0.945
A10: Premium / benchmark PMPM | C10: =Assumptions!$C$37 -> 1350 | D10: =Assumptions!$C$37 -> 1350 | E10: =Assumptions!$C$37 -> 1350 | F10: =Assumptions!$C$37 -> 1350 | G10: =Assumptions!$C$37 -> 1350 | H10: =Assumptions!$C$37 -> 1350 | I10: =Assumptions!$C$37 -> 1350 | J10: =Assumptions!$C$37 -> 1350 | ... N10: =Assumptions!$C$37 -> 1350
A11: New-clinic TCOC factor | C11: =Assumptions!$B$9+(Assumptions!$B$10-Assumptions!$B$9)*(0)/11 -> 1.06 | D11: =Assumptions!$B$9+(Assumptions!$B$10-Assumptions!$B$9)*(1)/11 -> 1.0545455 | E11: =Assumptions!$B$9+(Assumptions!$B$10-Assumptions!$B$9)*(2)/11 -> 1.0490909 | F11: =Assumptions!$B$9+(Assumptions!$B$10-Assumptions!$B$9)*(3)/11 -> 1.0436364 | G11: =Assumptions!$B$9+(Assumptions!$B$10-Assumptions!$B$9)*(4)/11 -> 1.0381818 | H11: =Assumptions!$B$9+(Assumptions!$B$10-Assumptions!$B$9)*(5)/11 -> 1.0327273 | I11: =Assumptions!$B$9+(Assumptions!$B$10-Assumptions!$B$9)*(6)/11 -> 1.0272727 | J11: =Assumptions!$B$9+(Assumptions!$B$10-Assumptions!$B$9)*(7)/11 -> 1.0218182 | K11: =Assumptions!$B$9+(Assumptions!$B$10-Assumptions!$B$9)*(8)/11 -> 1.0163636 | L11: =Assumptions!$B$9+(Assumptions!$B$10-Assumptions!$B$9)*(9)/11 -> 1.0109091 | M11: =Assumptions!$B$9+(Assumptions!$B$10-Assumptions!$B$9)*(10)/11 -> 1.0054545 | N11: =Assumptions!$B$9+(Assumptions!$B$10-Assumptions!$B$9)*(11)/11 -> 1
A12: Actual TCOC PMPM | C12: =Assumptions!$C$46*C11 -> 1187.2 | D12: =Assumptions!$C$46*D11 -> 1181.0909 | E12: =Assumptions!$C$46*E11 -> 1174.9818 | F12: =Assumptions!$C$46*F11 -> 1168.8727 | G12: =Assumptions!$C$46*G11 -> 1162.7636 | H12: =Assumptions!$C$46*H11 -> 1156.6545 | I12: =Assumptions!$C$46*I11 -> 1150.5455 | J12: =Assumptions!$C$46*J11 -> 1144.4364 | ... N12: =Assumptions!$C$46*N11 -> 1120
A14: REVENUE
A15: Global capitation | C15: =C6*C10*C9*Assumptions!$C$38 -> 0 | D15: =D6*D10*D9*Assumptions!$C$38 -> 0 | E15: =E6*E10*E9*Assumptions!$C$38 -> 0 | F15: =F6*F10*F9*Assumptions!$C$38 -> 0 | G15: =G6*G10*G9*Assumptions!$C$38 -> 0 | H15: =H6*H10*H9*Assumptions!$C$38 -> 0 | I15: =I6*I10*I9*Assumptions!$C$38 -> 0 | J15: =J6*J10*J9*Assumptions!$C$38 -> 0 | ... N15: =N6*N10*N9*Assumptions!$C$38 -> 0 | O15: =SUM(C15:N15) -> 0
A16: Care management | C16: =C6*Assumptions!$C$39 -> 24873.75 | D16: =D6*Assumptions!$C$39 -> 25122.487 | E16: =E6*Assumptions!$C$39 -> 25373.712 | F16: =F6*Assumptions!$C$39 -> 25627.449 | G16: =G6*Assumptions!$C$39 -> 25883.724 | H16: =H6*Assumptions!$C$39 -> 26142.561 | I16: =I6*Assumptions!$C$39 -> 26403.987 | J16: =J6*Assumptions!$C$39 -> 26668.027 | ... N16: =N6*Assumptions!$C$39 -> 27750.856 | O16: =SUM(C16:N16) -> 315461.41
A17: Primary care cap (PCCP) | C17: =C6*Assumptions!$C$40 -> 0 | D17: =D6*Assumptions!$C$40 -> 0 | E17: =E6*Assumptions!$C$40 -> 0 | F17: =F6*Assumptions!$C$40 -> 0 | G17: =G6*Assumptions!$C$40 -> 0 | H17: =H6*Assumptions!$C$40 -> 0 | I17: =I6*Assumptions!$C$40 -> 0 | J17: =J6*Assumptions!$C$40 -> 0 | ... N17: =N6*Assumptions!$C$40 -> 0 | O17: =SUM(C17:N17) -> 0
A18: FFS own services | C18: =C6*Assumptions!$C$41 -> 0 | D18: =D6*Assumptions!$C$41 -> 0 | E18: =E6*Assumptions!$C$41 -> 0 | F18: =F6*Assumptions!$C$41 -> 0 | G18: =G6*Assumptions!$C$41 -> 0 | H18: =H6*Assumptions!$C$41 -> 0 | I18: =I6*Assumptions!$C$41 -> 0 | J18: =J6*Assumptions!$C$41 -> 0 | ... N18: =N6*Assumptions!$C$41 -> 0 | O18: =SUM(C18:N18) -> 0
A19: Benchmark / target TCOC (memo) | C19: =C6*C10*C9*Assumptions!$C$42 -> 507722.98 | D19: =D6*D10*D9*Assumptions!$C$42 -> 512800.21 | E19: =E6*E10*E9*Assumptions!$C$42 -> 517928.22 | F19: =F6*F10*F9*Assumptions!$C$42 -> 523107.5 | G19: =G6*G10*G9*Assumptions!$C$42 -> 528338.57 | H19: =H6*H10*H9*Assumptions!$C$42 -> 533621.96 | I19: =I6*I10*I9*Assumptions!$C$42 -> 538958.18 | J19: =J6*J10*J9*Assumptions!$C$42 -> 544347.76 | ... N19: =N6*N10*N9*Assumptions!$C$42 -> 566450.46 | O19: =SUM(C19:N19) -> 6439198.3
A20: Actual TCOC (memo) | C20: =C6*C12 -> 536911.2 | D20: =D6*D12 -> 539489.85 | E20: =E6*E12 -> 542066.38 | F20: =F6*F12 -> 544640.49 | G20: =G6*G12 -> 547211.87 | H20: =H6*H12 -> 549780.22 | I20: =I6*I12 -> 552345.22 | J20: =J6*J12 -> 554906.54 | ... N20: =N6*N12 -> 565108.33 | O20: =SUM(C20:N20) -> 6612505.8
A21: Gross savings vs benchmark (memo) | C21: =C19-C20 -> -29188.215 | D21: =D19-D20 -> -26689.632 | E21: =E19-E20 -> -24138.159 | F21: =F19-F20 -> -21532.988 | G21: =G19-G20 -> -18873.299 | H21: =H19-H20 -> -16158.263 | I21: =I19-I20 -> -13387.04 | J21: =J19-J20 -> -10558.775 | ... N21: =N19-N20 -> 1342.1323 | O21: =SUM(C21:N21) -> -173307.55
A22: Shared savings / (loss) settlement | C22: =IF(Assumptions!$C$33=1,0,IF(C21>=0,C21*Assumptions!$C$43,C21*Assumptions!$C$44*Assumptions!$C$45)) -> -14594.108 | D22: =IF(Assumptions!$C$33=1,0,IF(D21>=0,D21*Assumptions!$C$43,D21*Assumptions!$C$44*Assumptions!$C$45)) -> -13344.816 | E22: =IF(Assumptions!$C$33=1,0,IF(E21>=0,E21*Assumptions!$C$43,E21*Assumptions!$C$44*Assumptions!$C$45)) -> -12069.08 | F22: =IF(Assumptions!$C$33=1,0,IF(F21>=0,F21*Assumptions!$C$43,F21*Assumptions!$C$44*Assumptions!$C$45)) -> -10766.494 | G22: =IF(Assumptions!$C$33=1,0,IF(G21>=0,G21*Assumptions!$C$43,G21*Assumptions!$C$44*Assumptions!$C$45)) -> -9436.6496 | H22: =IF(Assumptions!$C$33=1,0,IF(H21>=0,H21*Assumptions!$C$43,H21*Assumptions!$C$44*Assumptions!$C$45)) -> -8079.1317 | I22: =IF(Assumptions!$C$33=1,0,IF(I21>=0,I21*Assumptions!$C$43,I21*Assumptions!$C$44*Assumptions!$C$45)) -> -6693.5198 | J22: =IF(Assumptions!$C$33=1,0,IF(J21>=0,J21*Assumptions!$C$43,J21*Assumptions!$C$44*Assumptions!$C$45)) -> -5279.3877 | ... N22: =IF(Assumptions!$C$33=1,0,IF(N21>=0,N21*Assumptions!$C$43,N21*Assumptions!$C$44*Assumptions!$C$45)) -> 671.06614 | O22: =SUM(C22:N22) -> -86653.777
A23: TOTAL PROVIDER REVENUE | C23: =C15+C16+C17+C18+C22 -> 10279.642 | D23: =D15+D16+D17+D18+D22 -> 11777.671 | E23: =E15+E16+E17+E18+E22 -> 13304.633 | F23: =F15+F16+F17+F18+F22 -> 14860.956 | G23: =G15+G16+G17+G18+G22 -> 16447.074 | H23: =H15+H16+H17+H18+H22 -> 18063.43 | I23: =I15+I16+I17+I18+I22 -> 19710.467 | J23: =J15+J16+J17+J18+J22 -> 21388.639 | ... N23: =N15+N16+N17+N18+N22 -> 28421.922 | O23: =SUM(C23:N23) -> 228807.63
A25: PROVIDER MEDICAL COST (cash-bearing)
A26: Medical claims (full-cap only) | C26: =Assumptions!$C$33*C20 -> 0 | D26: =Assumptions!$C$33*D20 -> 0 | E26: =Assumptions!$C$33*E20 -> 0 | F26: =Assumptions!$C$33*F20 -> 0 | G26: =Assumptions!$C$33*G20 -> 0 | H26: =Assumptions!$C$33*H20 -> 0 | I26: =Assumptions!$C$33*I20 -> 0 | J26: =Assumptions!$C$33*J20 -> 0 | ... N26: =Assumptions!$C$33*N20 -> 0 | O26: =SUM(C26:N26) -> 0
A27: Stop-loss premium | C27: =Assumptions!$C$33*C6*Assumptions!$C$47 -> 0 | D27: =Assumptions!$C$33*D6*Assumptions!$C$47 -> 0 | E27: =Assumptions!$C$33*E6*Assumptions!$C$47 -> 0 | F27: =Assumptions!$C$33*F6*Assumptions!$C$47 -> 0 | G27: =Assumptions!$C$33*G6*Assumptions!$C$47 -> 0 | H27: =Assumptions!$C$33*H6*Assumptions!$C$47 -> 0 | I27: =Assumptions!$C$33*I6*Assumptions!$C$47 -> 0 | J27: =Assumptions!$C$33*J6*Assumptions!$C$47 -> 0 | ... N27: =Assumptions!$C$33*N6*Assumptions!$C$47 -> 0 | O27: =SUM(C27:N27) -> 0
A28: Stop-loss recoveries | C28: =-Assumptions!$C$33*C6*Assumptions!$C$48 -> 0 | D28: =-Assumptions!$C$33*D6*Assumptions!$C$48 -> 0 | E28: =-Assumptions!$C$33*E6*Assumptions!$C$48 -> 0 | F28: =-Assumptions!$C$33*F6*Assumptions!$C$48 -> 0 | G28: =-Assumptions!$C$33*G6*Assumptions!$C$48 -> 0 | H28: =-Assumptions!$C$33*H6*Assumptions!$C$48 -> 0 | I28: =-Assumptions!$C$33*I6*Assumptions!$C$48 -> 0 | J28: =-Assumptions!$C$33*J6*Assumptions!$C$48 -> 0 | ... N28: =-Assumptions!$C$33*N6*Assumptions!$C$48 -> 0 | O28: =SUM(C28:N28) -> 0
A29: TOTAL PROVIDER MEDICAL COST | C29: =C26+C27+C28 -> 0 | D29: =D26+D27+D28 -> 0 | E29: =E26+E27+E28 -> 0 | F29: =F26+F27+F28 -> 0 | G29: =G26+G27+G28 -> 0 | H29: =H26+H27+H28 -> 0 | I29: =I26+I27+I28 -> 0 | J29: =J26+J27+J28 -> 0 | ... N29: =N26+N27+N28 -> 0 | O29: =SUM(C29:N29) -> 0
A31: CONTRIBUTION & RATIOS
A32: Contribution margin | C32: =C23-C29 -> 10279.642 | D32: =D23-D29 -> 11777.671 | E32: =E23-E29 -> 13304.633 | F32: =F23-F29 -> 14860.956 | G32: =G23-G29 -> 16447.074 | H32: =H23-H29 -> 18063.43 | I32: =I23-I29 -> 19710.467 | J32: =J23-J29 -> 21388.639 | ... N32: =N23-N29 -> 28421.922 | O32: =SUM(C32:N32) -> 228807.63
A33: Medical loss ratio (TCOC / premium) | C33: =IF(C6=0,0,C20/(C6*C10*C9)) -> 0.93058985 | D33: =IF(D6=0,0,D20/(D6*D10*D9)) -> 0.92580122 | E33: =IF(E6=0,0,E20/(E6*E10*E9)) -> 0.9210126 | F33: =IF(F6=0,0,F20/(F6*F10*F9)) -> 0.91622397 | G33: =IF(G6=0,0,G20/(G6*G10*G9)) -> 0.91143534 | H33: =IF(H6=0,0,H20/(H6*H10*H9)) -> 0.90664671 | I33: =IF(I6=0,0,I20/(I6*I10*I9)) -> 0.90185809 | J33: =IF(J6=0,0,J20/(J6*J10*J9)) -> 0.89706946 | ... N33: =IF(N6=0,0,N20/(N6*N10*N9)) -> 0.87791495 | O33: =O20/SUMPRODUCT(C6:N6,C10:N10,C9:N9) -> 0.90368473
A34: Contribution PMPM | C34: =IF(C6=0,0,C32/C6) -> 22.73 | D34: =IF(D6=0,0,D32/D6) -> 25.784545 | E34: =IF(E6=0,0,E32/E6) -> 28.839091 | F34: =IF(F6=0,0,F32/F6) -> 31.893636 | G34: =IF(G6=0,0,G32/G6) -> 34.948182 | H34: =IF(H6=0,0,H32/H6) -> 38.002727 | I34: =IF(I6=0,0,I32/I6) -> 41.057273 | J34: =IF(J6=0,0,J32/J6) -> 44.111818 | ... N34: =IF(N6=0,0,N32/N6) -> 56.33 | O34: =O32/O6 -> 39.892105

Sheet C. Upside
A1: CONTRACT C — Upside-Only Shared Savings (60% upside, no downside)
A2: ($ unless noted) | C2: Jan | D2: Feb | E2: Mar | F2: Apr | G2: May | H2: Jun | I2: Jul | J2: Aug | K2: Sep | L2: Oct | M2: Nov | N2: Dec | O2: Year 1
A3: MEMBERSHIP
A4: Members — beginning | C4: =Assumptions!$D$34 -> 250 | D4: =C5 -> 252.5 | E4: =D5 -> 255.025 | F4: =E5 -> 257.57525 | G4: =F5 -> 260.151 | H4: =G5 -> 262.75251 | I4: =H5 -> 265.38004 | J4: =I5 -> 268.03384 | K4: =J5 -> 270.71418 | ... N4: =M5 -> 278.91709
A5: Members — ending | C5: =C4*(1+Assumptions!$D$35) -> 252.5 | D5: =D4*(1+Assumptions!$D$35) -> 255.025 | E5: =E4*(1+Assumptions!$D$35) -> 257.57525 | F5: =F4*(1+Assumptions!$D$35) -> 260.151 | G5: =G4*(1+Assumptions!$D$35) -> 262.75251 | H5: =H4*(1+Assumptions!$D$35) -> 265.38004 | I5: =I4*(1+Assumptions!$D$35) -> 268.03384 | J5: =J4*(1+Assumptions!$D$35) -> 270.71418 | ... N5: =N4*(1+Assumptions!$D$35) -> 281.70626 | O5: =N5 -> 281.70626
A6: Member-months (avg) | C6: =AVERAGE(C4,C5) -> 251.25 | D6: =AVERAGE(D4,D5) -> 253.7625 | E6: =AVERAGE(E4,E5) -> 256.30012 | F6: =AVERAGE(F4,F5) -> 258.86313 | G6: =AVERAGE(G4,G5) -> 261.45176 | H6: =AVERAGE(H4,H5) -> 264.06628 | I6: =AVERAGE(I4,I5) -> 266.70694 | J6: =AVERAGE(J4,J5) -> 269.37401 | ... N6: =AVERAGE(N4,N5) -> 280.31167 | O6: =SUM(C6:N6) -> 3186.4789
A8: LEVERS — RISK & TCOC
A9: RAF (risk score, Yr-1 cohort) | C9: =Assumptions!$D$36*Assumptions!$B$52 -> 0.9 | D9: =Assumptions!$D$36*Assumptions!$B$52 -> 0.9 | E9: =Assumptions!$D$36*Assumptions!$B$52 -> 0.9 | F9: =Assumptions!$D$36*Assumptions!$B$52 -> 0.9 | G9: =Assumptions!$D$36*Assumptions!$B$52 -> 0.9 | H9: =Assumptions!$D$36*Assumptions!$B$52 -> 0.9 | I9: =Assumptions!$D$36*Assumptions!$B$52 -> 0.9 | J9: =Assumptions!$D$36*Assumptions!$B$52 -> 0.9 | ... N9: =Assumptions!$D$36*Assumptions!$B$52 -> 0.9
A10: Premium / benchmark PMPM | C10: =Assumptions!$D$37 -> 1250 | D10: =Assumptions!$D$37 -> 1250 | E10: =Assumptions!$D$37 -> 1250 | F10: =Assumptions!$D$37 -> 1250 | G10: =Assumptions!$D$37 -> 1250 | H10: =Assumptions!$D$37 -> 1250 | I10: =Assumptions!$D$37 -> 1250 | J10: =Assumptions!$D$37 -> 1250 | ... N10: =Assumptions!$D$37 -> 1250
A11: New-clinic TCOC factor | C11: =Assumptions!$B$9+(Assumptions!$B$10-Assumptions!$B$9)*(0)/11 -> 1.06 | D11: =Assumptions!$B$9+(Assumptions!$B$10-Assumptions!$B$9)*(1)/11 -> 1.0545455 | E11: =Assumptions!$B$9+(Assumptions!$B$10-Assumptions!$B$9)*(2)/11 -> 1.0490909 | F11: =Assumptions!$B$9+(Assumptions!$B$10-Assumptions!$B$9)*(3)/11 -> 1.0436364 | G11: =Assumptions!$B$9+(Assumptions!$B$10-Assumptions!$B$9)*(4)/11 -> 1.0381818 | H11: =Assumptions!$B$9+(Assumptions!$B$10-Assumptions!$B$9)*(5)/11 -> 1.0327273 | I11: =Assumptions!$B$9+(Assumptions!$B$10-Assumptions!$B$9)*(6)/11 -> 1.0272727 | J11: =Assumptions!$B$9+(Assumptions!$B$10-Assumptions!$B$9)*(7)/11 -> 1.0218182 | K11: =Assumptions!$B$9+(Assumptions!$B$10-Assumptions!$B$9)*(8)/11 -> 1.0163636 | L11: =Assumptions!$B$9+(Assumptions!$B$10-Assumptions!$B$9)*(9)/11 -> 1.0109091 | M11: =Assumptions!$B$9+(Assumptions!$B$10-Assumptions!$B$9)*(10)/11 -> 1.0054545 | N11: =Assumptions!$B$9+(Assumptions!$B$10-Assumptions!$B$9)*(11)/11 -> 1
A12: Actual TCOC PMPM | C12: =Assumptions!$D$46*C11 -> 1123.6 | D12: =Assumptions!$D$46*D11 -> 1117.8182 | E12: =Assumptions!$D$46*E11 -> 1112.0364 | F12: =Assumptions!$D$46*F11 -> 1106.2545 | G12: =Assumptions!$D$46*G11 -> 1100.4727 | H12: =Assumptions!$D$46*H11 -> 1094.6909 | I12: =Assumptions!$D$46*I11 -> 1088.9091 | J12: =Assumptions!$D$46*J11 -> 1083.1273 | ... N12: =Assumptions!$D$46*N11 -> 1060
A14: REVENUE
A15: Global capitation | C15: =C6*C10*C9*Assumptions!$D$38 -> 0 | D15: =D6*D10*D9*Assumptions!$D$38 -> 0 | E15: =E6*E10*E9*Assumptions!$D$38 -> 0 | F15: =F6*F10*F9*Assumptions!$D$38 -> 0 | G15: =G6*G10*G9*Assumptions!$D$38 -> 0 | H15: =H6*H10*H9*Assumptions!$D$38 -> 0 | I15: =I6*I10*I9*Assumptions!$D$38 -> 0 | J15: =J6*J10*J9*Assumptions!$D$38 -> 0 | ... N15: =N6*N10*N9*Assumptions!$D$38 -> 0 | O15: =SUM(C15:N15) -> 0
A16: Care management | C16: =C6*Assumptions!$D$39 -> 0 | D16: =D6*Assumptions!$D$39 -> 0 | E16: =E6*Assumptions!$D$39 -> 0 | F16: =F6*Assumptions!$D$39 -> 0 | G16: =G6*Assumptions!$D$39 -> 0 | H16: =H6*Assumptions!$D$39 -> 0 | I16: =I6*Assumptions!$D$39 -> 0 | J16: =J6*Assumptions!$D$39 -> 0 | ... N16: =N6*Assumptions!$D$39 -> 0 | O16: =SUM(C16:N16) -> 0
A17: Primary care cap (PCCP) | C17: =C6*Assumptions!$D$40 -> 0 | D17: =D6*Assumptions!$D$40 -> 0 | E17: =E6*Assumptions!$D$40 -> 0 | F17: =F6*Assumptions!$D$40 -> 0 | G17: =G6*Assumptions!$D$40 -> 0 | H17: =H6*Assumptions!$D$40 -> 0 | I17: =I6*Assumptions!$D$40 -> 0 | J17: =J6*Assumptions!$D$40 -> 0 | ... N17: =N6*Assumptions!$D$40 -> 0 | O17: =SUM(C17:N17) -> 0
A18: FFS own services | C18: =C6*Assumptions!$D$41 -> 12562.5 | D18: =D6*Assumptions!$D$41 -> 12688.125 | E18: =E6*Assumptions!$D$41 -> 12815.006 | F18: =F6*Assumptions!$D$41 -> 12943.156 | G18: =G6*Assumptions!$D$41 -> 13072.588 | H18: =H6*Assumptions!$D$41 -> 13203.314 | I18: =I6*Assumptions!$D$41 -> 13335.347 | J18: =J6*Assumptions!$D$41 -> 13468.7 | ... N18: =N6*Assumptions!$D$41 -> 14015.584 | O18: =SUM(C18:N18) -> 159323.94
A19: Benchmark / target TCOC (memo) | C19: =C6*C10*C9*Assumptions!$D$42 -> 254390.62 | D19: =D6*D10*D9*Assumptions!$D$42 -> 256934.53 | E19: =E6*E10*E9*Assumptions!$D$42 -> 259503.88 | F19: =F6*F10*F9*Assumptions!$D$42 -> 262098.92 | G19: =G6*G10*G9*Assumptions!$D$42 -> 264719.9 | H19: =H6*H10*H9*Assumptions!$D$42 -> 267367.1 | I19: =I6*I10*I9*Assumptions!$D$42 -> 270040.77 | J19: =J6*J10*J9*Assumptions!$D$42 -> 272741.18 | ... N19: =N6*N10*N9*Assumptions!$D$42 -> 283815.57 | O19: =SUM(C19:N19) -> 3226309.9
A20: Actual TCOC (memo) | C20: =C6*C12 -> 282304.5 | D20: =D6*D12 -> 283660.34 | E20: =E6*E12 -> 285015.06 | F20: =F6*F12 -> 286368.51 | G20: =G6*G12 -> 287720.53 | H20: =H6*H12 -> 289070.95 | I20: =I6*I12 -> 290419.61 | J20: =J6*J12 -> 291766.33 | ... N20: =N6*N12 -> 297130.37 | O20: =SUM(C20:N20) -> 3476813.6
A21: Gross savings vs benchmark (memo) | C21: =C19-C20 -> -27913.875 | D21: =D19-D20 -> -26725.805 | E21: =E19-E20 -> -25511.182 | F21: =F19-F20 -> -24269.595 | G21: =G19-G20 -> -23000.624 | H21: =H19-H20 -> -21703.847 | I21: =I19-I20 -> -20378.835 | J21: =J19-J20 -> -19025.151 | ... N21: =N19-N20 -> -13314.804 | O21: =SUM(C21:N21) -> -250503.72
A22: Shared savings / (loss) settlement | C22: =IF(Assumptions!$D$33=1,0,IF(C21>=0,C21*Assumptions!$D$43,C21*Assumptions!$D$44*Assumptions!$D$45)) -> 0 | D22: =IF(Assumptions!$D$33=1,0,IF(D21>=0,D21*Assumptions!$D$43,D21*Assumptions!$D$44*Assumptions!$D$45)) -> 0 | E22: =IF(Assumptions!$D$33=1,0,IF(E21>=0,E21*Assumptions!$D$43,E21*Assumptions!$D$44*Assumptions!$D$45)) -> 0 | F22: =IF(Assumptions!$D$33=1,0,IF(F21>=0,F21*Assumptions!$D$43,F21*Assumptions!$D$44*Assumptions!$D$45)) -> 0 | G22: =IF(Assumptions!$D$33=1,0,IF(G21>=0,G21*Assumptions!$D$43,G21*Assumptions!$D$44*Assumptions!$D$45)) -> 0 | H22: =IF(Assumptions!$D$33=1,0,IF(H21>=0,H21*Assumptions!$D$43,H21*Assumptions!$D$44*Assumptions!$D$45)) -> 0 | I22: =IF(Assumptions!$D$33=1,0,IF(I21>=0,I21*Assumptions!$D$43,I21*Assumptions!$D$44*Assumptions!$D$45)) -> 0 | J22: =IF(Assumptions!$D$33=1,0,IF(J21>=0,J21*Assumptions!$D$43,J21*Assumptions!$D$44*Assumptions!$D$45)) -> 0 | ... N22: =IF(Assumptions!$D$33=1,0,IF(N21>=0,N21*Assumptions!$D$43,N21*Assumptions!$D$44*Assumptions!$D$45)) -> 0 | O22: =SUM(C22:N22) -> 0
A23: TOTAL PROVIDER REVENUE | C23: =C15+C16+C17+C18+C22 -> 12562.5 | D23: =D15+D16+D17+D18+D22 -> 12688.125 | E23: =E15+E16+E17+E18+E22 -> 12815.006 | F23: =F15+F16+F17+F18+F22 -> 12943.156 | G23: =G15+G16+G17+G18+G22 -> 13072.588 | H23: =H15+H16+H17+H18+H22 -> 13203.314 | I23: =I15+I16+I17+I18+I22 -> 13335.347 | J23: =J15+J16+J17+J18+J22 -> 13468.7 | ... N23: =N15+N16+N17+N18+N22 -> 14015.584 | O23: =SUM(C23:N23) -> 159323.94
A25: PROVIDER MEDICAL COST (cash-bearing)
A26: Medical claims (full-cap only) | C26: =Assumptions!$D$33*C20 -> 0 | D26: =Assumptions!$D$33*D20 -> 0 | E26: =Assumptions!$D$33*E20 -> 0 | F26: =Assumptions!$D$33*F20 -> 0 | G26: =Assumptions!$D$33*G20 -> 0 | H26: =Assumptions!$D$33*H20 -> 0 | I26: =Assumptions!$D$33*I20 -> 0 | J26: =Assumptions!$D$33*J20 -> 0 | ... N26: =Assumptions!$D$33*N20 -> 0 | O26: =SUM(C26:N26) -> 0
A27: Stop-loss premium | C27: =Assumptions!$D$33*C6*Assumptions!$D$47 -> 0 | D27: =Assumptions!$D$33*D6*Assumptions!$D$47 -> 0 | E27: =Assumptions!$D$33*E6*Assumptions!$D$47 -> 0 | F27: =Assumptions!$D$33*F6*Assumptions!$D$47 -> 0 | G27: =Assumptions!$D$33*G6*Assumptions!$D$47 -> 0 | H27: =Assumptions!$D$33*H6*Assumptions!$D$47 -> 0 | I27: =Assumptions!$D$33*I6*Assumptions!$D$47 -> 0 | J27: =Assumptions!$D$33*J6*Assumptions!$D$47 -> 0 | ... N27: =Assumptions!$D$33*N6*Assumptions!$D$47 -> 0 | O27: =SUM(C27:N27) -> 0
A28: Stop-loss recoveries | C28: =-Assumptions!$D$33*C6*Assumptions!$D$48 -> 0 | D28: =-Assumptions!$D$33*D6*Assumptions!$D$48 -> 0 | E28: =-Assumptions!$D$33*E6*Assumptions!$D$48 -> 0 | F28: =-Assumptions!$D$33*F6*Assumptions!$D$48 -> 0 | G28: =-Assumptions!$D$33*G6*Assumptions!$D$48 -> 0 | H28: =-Assumptions!$D$33*H6*Assumptions!$D$48 -> 0 | I28: =-Assumptions!$D$33*I6*Assumptions!$D$48 -> 0 | J28: =-Assumptions!$D$33*J6*Assumptions!$D$48 -> 0 | ... N28: =-Assumptions!$D$33*N6*Assumptions!$D$48 -> 0 | O28: =SUM(C28:N28) -> 0
A29: TOTAL PROVIDER MEDICAL COST | C29: =C26+C27+C28 -> 0 | D29: =D26+D27+D28 -> 0 | E29: =E26+E27+E28 -> 0 | F29: =F26+F27+F28 -> 0 | G29: =G26+G27+G28 -> 0 | H29: =H26+H27+H28 -> 0 | I29: =I26+I27+I28 -> 0 | J29: =J26+J27+J28 -> 0 | ... N29: =N26+N27+N28 -> 0 | O29: =SUM(C29:N29) -> 0
A31: CONTRIBUTION & RATIOS
A32: Contribution margin | C32: =C23-C29 -> 12562.5 | D32: =D23-D29 -> 12688.125 | E32: =E23-E29 -> 12815.006 | F32: =F23-F29 -> 12943.156 | G32: =G23-G29 -> 13072.588 | H32: =H23-H29 -> 13203.314 | I32: =I23-I29 -> 13335.347 | J32: =J23-J29 -> 13468.7 | ... N32: =N23-N29 -> 14015.584 | O32: =SUM(C32:N32) -> 159323.94
A33: Medical loss ratio (TCOC / premium) | C33: =IF(C6=0,0,C20/(C6*C10*C9)) -> 0.99875556 | D33: =IF(D6=0,0,D20/(D6*D10*D9)) -> 0.99361616 | E33: =IF(E6=0,0,E20/(E6*E10*E9)) -> 0.98847677 | F33: =IF(F6=0,0,F20/(F6*F10*F9)) -> 0.98333737 | G33: =IF(G6=0,0,G20/(G6*G10*G9)) -> 0.97819798 | H33: =IF(H6=0,0,H20/(H6*H10*H9)) -> 0.97305859 | I33: =IF(I6=0,0,I20/(I6*I10*I9)) -> 0.96791919 | J33: =IF(J6=0,0,J20/(J6*J10*J9)) -> 0.9627798 | ... N33: =IF(N6=0,0,N20/(N6*N10*N9)) -> 0.94222222 | O33: =O20/SUMPRODUCT(C6:N6,C10:N10,C9:N9) -> 0.96987963
A34: Contribution PMPM | C34: =IF(C6=0,0,C32/C6) -> 50 | D34: =IF(D6=0,0,D32/D6) -> 50 | E34: =IF(E6=0,0,E32/E6) -> 50 | F34: =IF(F6=0,0,F32/F6) -> 50 | G34: =IF(G6=0,0,G32/G6) -> 50 | H34: =IF(H6=0,0,H32/H6) -> 50 | I34: =IF(I6=0,0,I32/I6) -> 50 | J34: =IF(J6=0,0,J32/J6) -> 50 | ... N34: =IF(N6=0,0,N32/N6) -> 50 | O34: =O32/O6 -> 50

Sheet D. REACH
A1: CONTRACT D — ACO REACH Professional (PCCP + 50/50)
A2: ($ unless noted) | C2: Jan | D2: Feb | E2: Mar | F2: Apr | G2: May | H2: Jun | I2: Jul | J2: Aug | K2: Sep | L2: Oct | M2: Nov | N2: Dec | O2: Year 1
A3: MEMBERSHIP
A4: Members — beginning | C4: =Assumptions!$E$34 -> 200 | D4: =C5 -> 203 | E4: =D5 -> 206.045 | F4: =E5 -> 209.13567 | G4: =F5 -> 212.27271 | H4: =G5 -> 215.4568 | I4: =H5 -> 218.68865 | J4: =I5 -> 221.96898 | K4: =J5 -> 225.29852 | ... N4: =M5 -> 235.58979
A5: Members — ending | C5: =C4*(1+Assumptions!$E$35) -> 203 | D5: =D4*(1+Assumptions!$E$35) -> 206.045 | E5: =E4*(1+Assumptions!$E$35) -> 209.13567 | F5: =F4*(1+Assumptions!$E$35) -> 212.27271 | G5: =G4*(1+Assumptions!$E$35) -> 215.4568 | H5: =H4*(1+Assumptions!$E$35) -> 218.68865 | I5: =I4*(1+Assumptions!$E$35) -> 221.96898 | J5: =J4*(1+Assumptions!$E$35) -> 225.29852 | ... N5: =N4*(1+Assumptions!$E$35) -> 239.12363 | O5: =N5 -> 239.12363
A6: Member-months (avg) | C6: =AVERAGE(C4,C5) -> 201.5 | D6: =AVERAGE(D4,D5) -> 204.5225 | E6: =AVERAGE(E4,E5) -> 207.59034 | F6: =AVERAGE(F4,F5) -> 210.70419 | G6: =AVERAGE(G4,G5) -> 213.86476 | H6: =AVERAGE(H4,H5) -> 217.07273 | I6: =AVERAGE(I4,I5) -> 220.32882 | J6: =AVERAGE(J4,J5) -> 223.63375 | ... N6: =AVERAGE(N4,N5) -> 237.35671 | O6: =SUM(C6:N6) -> 2627.8041
A8: LEVERS — RISK & TCOC
A9: RAF (risk score, Yr-1 cohort) | C9: =Assumptions!$E$36*Assumptions!$B$52 -> 0.945 | D9: =Assumptions!$E$36*Assumptions!$B$52 -> 0.945 | E9: =Assumptions!$E$36*Assumptions!$B$52 -> 0.945 | F9: =Assumptions!$E$36*Assumptions!$B$52 -> 0.945 | G9: =Assumptions!$E$36*Assumptions!$B$52 -> 0.945 | H9: =Assumptions!$E$36*Assumptions!$B$52 -> 0.945 | I9: =Assumptions!$E$36*Assumptions!$B$52 -> 0.945 | J9: =Assumptions!$E$36*Assumptions!$B$52 -> 0.945 | ... N9: =Assumptions!$E$36*Assumptions!$B$52 -> 0.945
A10: Premium / benchmark PMPM | C10: =Assumptions!$E$37 -> 1150 | D10: =Assumptions!$E$37 -> 1150 | E10: =Assumptions!$E$37 -> 1150 | F10: =Assumptions!$E$37 -> 1150 | G10: =Assumptions!$E$37 -> 1150 | H10: =Assumptions!$E$37 -> 1150 | I10: =Assumptions!$E$37 -> 1150 | J10: =Assumptions!$E$37 -> 1150 | ... N10: =Assumptions!$E$37 -> 1150
A11: New-clinic TCOC factor | C11: =Assumptions!$B$9+(Assumptions!$B$10-Assumptions!$B$9)*(0)/11 -> 1.06 | D11: =Assumptions!$B$9+(Assumptions!$B$10-Assumptions!$B$9)*(1)/11 -> 1.0545455 | E11: =Assumptions!$B$9+(Assumptions!$B$10-Assumptions!$B$9)*(2)/11 -> 1.0490909 | F11: =Assumptions!$B$9+(Assumptions!$B$10-Assumptions!$B$9)*(3)/11 -> 1.0436364 | G11: =Assumptions!$B$9+(Assumptions!$B$10-Assumptions!$B$9)*(4)/11 -> 1.0381818 | H11: =Assumptions!$B$9+(Assumptions!$B$10-Assumptions!$B$9)*(5)/11 -> 1.0327273 | I11: =Assumptions!$B$9+(Assumptions!$B$10-Assumptions!$B$9)*(6)/11 -> 1.0272727 | J11: =Assumptions!$B$9+(Assumptions!$B$10-Assumptions!$B$9)*(7)/11 -> 1.0218182 | K11: =Assumptions!$B$9+(Assumptions!$B$10-Assumptions!$B$9)*(8)/11 -> 1.0163636 | L11: =Assumptions!$B$9+(Assumptions!$B$10-Assumptions!$B$9)*(9)/11 -> 1.0109091 | M11: =Assumptions!$B$9+(Assumptions!$B$10-Assumptions!$B$9)*(10)/11 -> 1.0054545 | N11: =Assumptions!$B$9+(Assumptions!$B$10-Assumptions!$B$9)*(11)/11 -> 1
A12: Actual TCOC PMPM | C12: =Assumptions!$E$46*C11 -> 1070.6 | D12: =Assumptions!$E$46*D11 -> 1065.0909 | E12: =Assumptions!$E$46*E11 -> 1059.5818 | F12: =Assumptions!$E$46*F11 -> 1054.0727 | G12: =Assumptions!$E$46*G11 -> 1048.5636 | H12: =Assumptions!$E$46*H11 -> 1043.0545 | I12: =Assumptions!$E$46*I11 -> 1037.5455 | J12: =Assumptions!$E$46*J11 -> 1032.0364 | ... N12: =Assumptions!$E$46*N11 -> 1010
A14: REVENUE
A15: Global capitation | C15: =C6*C10*C9*Assumptions!$E$38 -> 0 | D15: =D6*D10*D9*Assumptions!$E$38 -> 0 | E15: =E6*E10*E9*Assumptions!$E$38 -> 0 | F15: =F6*F10*F9*Assumptions!$E$38 -> 0 | G15: =G6*G10*G9*Assumptions!$E$38 -> 0 | H15: =H6*H10*H9*Assumptions!$E$38 -> 0 | I15: =I6*I10*I9*Assumptions!$E$38 -> 0 | J15: =J6*J10*J9*Assumptions!$E$38 -> 0 | ... N15: =N6*N10*N9*Assumptions!$E$38 -> 0 | O15: =SUM(C15:N15) -> 0
A16: Care management | C16: =C6*Assumptions!$E$39 -> 0 | D16: =D6*Assumptions!$E$39 -> 0 | E16: =E6*Assumptions!$E$39 -> 0 | F16: =F6*Assumptions!$E$39 -> 0 | G16: =G6*Assumptions!$E$39 -> 0 | H16: =H6*Assumptions!$E$39 -> 0 | I16: =I6*Assumptions!$E$39 -> 0 | J16: =J6*Assumptions!$E$39 -> 0 | ... N16: =N6*Assumptions!$E$39 -> 0 | O16: =SUM(C16:N16) -> 0
A17: Primary care cap (PCCP) | C17: =C6*Assumptions!$E$40 -> 16120 | D17: =D6*Assumptions!$E$40 -> 16361.8 | E17: =E6*Assumptions!$E$40 -> 16607.227 | F17: =F6*Assumptions!$E$40 -> 16856.335 | G17: =G6*Assumptions!$E$40 -> 17109.18 | H17: =H6*Assumptions!$E$40 -> 17365.818 | I17: =I6*Assumptions!$E$40 -> 17626.305 | J17: =J6*Assumptions!$E$40 -> 17890.7 | ... N17: =N6*Assumptions!$E$40 -> 18988.537 | O17: =SUM(C17:N17) -> 210224.33
A18: FFS own services | C18: =C6*Assumptions!$E$41 -> 0 | D18: =D6*Assumptions!$E$41 -> 0 | E18: =E6*Assumptions!$E$41 -> 0 | F18: =F6*Assumptions!$E$41 -> 0 | G18: =G6*Assumptions!$E$41 -> 0 | H18: =H6*Assumptions!$E$41 -> 0 | I18: =I6*Assumptions!$E$41 -> 0 | J18: =J6*Assumptions!$E$41 -> 0 | ... N18: =N6*Assumptions!$E$41 -> 0 | O18: =SUM(C18:N18) -> 0
A19: Benchmark / target TCOC (memo) | C19: =C6*C10*C9*Assumptions!$E$42 -> 214600.52 | D19: =D6*D10*D9*Assumptions!$E$42 -> 217819.53 | E19: =E6*E10*E9*Assumptions!$E$42 -> 221086.82 | F19: =F6*F10*F9*Assumptions!$E$42 -> 224403.13 | G19: =G6*G10*G9*Assumptions!$E$42 -> 227769.17 | H19: =H6*H10*H9*Assumptions!$E$42 -> 231185.71 | I19: =I6*I10*I9*Assumptions!$E$42 -> 234653.5 | J19: =J6*J10*J9*Assumptions!$E$42 -> 238173.3 | ... N19: =N6*N10*N9*Assumptions!$E$42 -> 252788.46 | O19: =SUM(C19:N19) -> 2798650.8
A20: Actual TCOC (memo) | C20: =C6*C12 -> 215725.9 | D20: =D6*D12 -> 217835.06 | E20: =E6*E12 -> 219958.95 | F20: =F6*F12 -> 222097.54 | G20: =G6*G12 -> 224250.81 | H20: =H6*H12 -> 226418.69 | I20: =I6*I12 -> 228601.16 | J20: =J6*J12 -> 230798.16 | ... N20: =N6*N12 -> 239730.28 | O20: =SUM(C20:N20) -> 2731137.5
A21: Gross savings vs benchmark (memo) | C21: =C19-C20 -> -1125.3775 | D21: =D19-D20 -> -15.525117 | E21: =E19-E20 -> 1127.876 | F21: =F19-F20 -> 2305.5827 | G21: =G19-G20 -> 3518.3669 | H21: =H19-H20 -> 4767.0157 | I21: =I19-I20 -> 6052.3325 | J21: =J19-J20 -> 7375.1361 | ... N21: =N19-N20 -> 13058.179 | O21: =SUM(C21:N21) -> 67513.318
A22: Shared savings / (loss) settlement | C22: =IF(Assumptions!$E$33=1,0,IF(C21>=0,C21*Assumptions!$E$43,C21*Assumptions!$E$44*Assumptions!$E$45)) -> -562.68875 | D22: =IF(Assumptions!$E$33=1,0,IF(D21>=0,D21*Assumptions!$E$43,D21*Assumptions!$E$44*Assumptions!$E$45)) -> -7.7625585 | E22: =IF(Assumptions!$E$33=1,0,IF(E21>=0,E21*Assumptions!$E$43,E21*Assumptions!$E$44*Assumptions!$E$45)) -> 563.93802 | F22: =IF(Assumptions!$E$33=1,0,IF(F21>=0,F21*Assumptions!$E$43,F21*Assumptions!$E$44*Assumptions!$E$45)) -> 1152.7914 | G22: =IF(Assumptions!$E$33=1,0,IF(G21>=0,G21*Assumptions!$E$43,G21*Assumptions!$E$44*Assumptions!$E$45)) -> 1759.1834 | H22: =IF(Assumptions!$E$33=1,0,IF(H21>=0,H21*Assumptions!$E$43,H21*Assumptions!$E$44*Assumptions!$E$45)) -> 2383.5079 | I22: =IF(Assumptions!$E$33=1,0,IF(I21>=0,I21*Assumptions!$E$43,I21*Assumptions!$E$44*Assumptions!$E$45)) -> 3026.1662 | J22: =IF(Assumptions!$E$33=1,0,IF(J21>=0,J21*Assumptions!$E$43,J21*Assumptions!$E$44*Assumptions!$E$45)) -> 3687.5681 | ... N22: =IF(Assumptions!$E$33=1,0,IF(N21>=0,N21*Assumptions!$E$43,N21*Assumptions!$E$44*Assumptions!$E$45)) -> 6529.0897 | O22: =SUM(C22:N22) -> 33756.659
A23: TOTAL PROVIDER REVENUE | C23: =C15+C16+C17+C18+C22 -> 15557.311 | D23: =D15+D16+D17+D18+D22 -> 16354.037 | E23: =E15+E16+E17+E18+E22 -> 17171.165 | F23: =F15+F16+F17+F18+F22 -> 18009.127 | G23: =G15+G16+G17+G18+G22 -> 18868.364 | H23: =H15+H16+H17+H18+H22 -> 19749.326 | I23: =I15+I16+I17+I18+I22 -> 20652.472 | J23: =J15+J16+J17+J18+J22 -> 21578.268 | ... N23: =N15+N16+N17+N18+N22 -> 25517.627 | O23: =SUM(C23:N23) -> 243980.99
A25: PROVIDER MEDICAL COST (cash-bearing)
A26: Medical claims (full-cap only) | C26: =Assumptions!$E$33*C20 -> 0 | D26: =Assumptions!$E$33*D20 -> 0 | E26: =Assumptions!$E$33*E20 -> 0 | F26: =Assumptions!$E$33*F20 -> 0 | G26: =Assumptions!$E$33*G20 -> 0 | H26: =Assumptions!$E$33*H20 -> 0 | I26: =Assumptions!$E$33*I20 -> 0 | J26: =Assumptions!$E$33*J20 -> 0 | ... N26: =Assumptions!$E$33*N20 -> 0 | O26: =SUM(C26:N26) -> 0
A27: Stop-loss premium | C27: =Assumptions!$E$33*C6*Assumptions!$E$47 -> 0 | D27: =Assumptions!$E$33*D6*Assumptions!$E$47 -> 0 | E27: =Assumptions!$E$33*E6*Assumptions!$E$47 -> 0 | F27: =Assumptions!$E$33*F6*Assumptions!$E$47 -> 0 | G27: =Assumptions!$E$33*G6*Assumptions!$E$47 -> 0 | H27: =Assumptions!$E$33*H6*Assumptions!$E$47 -> 0 | I27: =Assumptions!$E$33*I6*Assumptions!$E$47 -> 0 | J27: =Assumptions!$E$33*J6*Assumptions!$E$47 -> 0 | ... N27: =Assumptions!$E$33*N6*Assumptions!$E$47 -> 0 | O27: =SUM(C27:N27) -> 0
A28: Stop-loss recoveries | C28: =-Assumptions!$E$33*C6*Assumptions!$E$48 -> 0 | D28: =-Assumptions!$E$33*D6*Assumptions!$E$48 -> 0 | E28: =-Assumptions!$E$33*E6*Assumptions!$E$48 -> 0 | F28: =-Assumptions!$E$33*F6*Assumptions!$E$48 -> 0 | G28: =-Assumptions!$E$33*G6*Assumptions!$E$48 -> 0 | H28: =-Assumptions!$E$33*H6*Assumptions!$E$48 -> 0 | I28: =-Assumptions!$E$33*I6*Assumptions!$E$48 -> 0 | J28: =-Assumptions!$E$33*J6*Assumptions!$E$48 -> 0 | ... N28: =-Assumptions!$E$33*N6*Assumptions!$E$48 -> 0 | O28: =SUM(C28:N28) -> 0
A29: TOTAL PROVIDER MEDICAL COST | C29: =C26+C27+C28 -> 0 | D29: =D26+D27+D28 -> 0 | E29: =E26+E27+E28 -> 0 | F29: =F26+F27+F28 -> 0 | G29: =G26+G27+G28 -> 0 | H29: =H26+H27+H28 -> 0 | I29: =I26+I27+I28 -> 0 | J29: =J26+J27+J28 -> 0 | ... N29: =N26+N27+N28 -> 0 | O29: =SUM(C29:N29) -> 0
A31: CONTRIBUTION & RATIOS
A32: Contribution margin | C32: =C23-C29 -> 15557.311 | D32: =D23-D29 -> 16354.037 | E32: =E23-E29 -> 17171.165 | F32: =F23-F29 -> 18009.127 | G32: =G23-G29 -> 18868.364 | H32: =H23-H29 -> 19749.326 | I32: =I23-I29 -> 20652.472 | J32: =J23-J29 -> 21578.268 | ... N32: =N23-N29 -> 25517.627 | O32: =SUM(C32:N32) -> 243980.99
A33: Medical loss ratio (TCOC / premium) | C33: =IF(C6=0,0,C20/(C6*C10*C9)) -> 0.98513918 | D33: =IF(D6=0,0,D20/(D6*D10*D9)) -> 0.98006985 | E33: =IF(E6=0,0,E20/(E6*E10*E9)) -> 0.97500052 | F33: =IF(F6=0,0,F20/(F6*F10*F9)) -> 0.9699312 | G33: =IF(G6=0,0,G20/(G6*G10*G9)) -> 0.96486187 | H33: =IF(H6=0,0,H20/(H6*H10*H9)) -> 0.95979254 | I33: =IF(I6=0,0,I20/(I6*I10*I9)) -> 0.95472322 | J33: =IF(J6=0,0,J20/(J6*J10*J9)) -> 0.94965389 | ... N33: =IF(N6=0,0,N20/(N6*N10*N9)) -> 0.92937658 | O33: =O20/SUMPRODUCT(C6:N6,C10:N10,C9:N9) -> 0.95635895
A34: Contribution PMPM | C34: =IF(C6=0,0,C32/C6) -> 77.2075 | D34: =IF(D6=0,0,D32/D6) -> 79.962045 | E34: =IF(E6=0,0,E32/E6) -> 82.716591 | F34: =IF(F6=0,0,F32/F6) -> 85.471136 | G34: =IF(G6=0,0,G32/G6) -> 88.225682 | H34: =IF(H6=0,0,H32/H6) -> 90.980227 | I34: =IF(I6=0,0,I32/I6) -> 93.734773 | J34: =IF(J6=0,0,J32/J6) -> 96.489318 | ... N34: =IF(N6=0,0,N32/N6) -> 107.5075 | O34: =O32/O6 -> 92.845957

Sheet P&L (Monthly)
A1: CONSOLIDATED P&L — Year 1 (Monthly)
C2: Jan | D2: Feb | E2: Mar | F2: Apr | G2: May | H2: Jun | I2: Jul | J2: Aug | K2: Sep | L2: Oct | M2: Nov | N2: Dec | O2: Year 1
A3: MEMBERSHIP
A4: Member-months (avg) | C4: ='A. Full Cap'!C6+'B. Two-Sided'!C6+'C. Upside'!C6+'D. REACH'!C6 -> 4523 | D4: ='A. Full Cap'!D6+'B. Two-Sided'!D6+'C. Upside'!D6+'D. REACH'!D6 -> 4569.2375 | E4: ='A. Full Cap'!E6+'B. Two-Sided'!E6+'C. Upside'!E6+'D. REACH'!E6 -> 4615.9525 | F4: ='A. Full Cap'!F6+'B. Two-Sided'!F6+'C. Upside'!F6+'D. REACH'!F6 -> 4663.15 | G4: ='A. Full Cap'!G6+'B. Two-Sided'!G6+'C. Upside'!G6+'D. REACH'!G6 -> 4710.835 | H4: ='A. Full Cap'!H6+'B. Two-Sided'!H6+'C. Upside'!H6+'D. REACH'!H6 -> 4759.0127 | I4: ='A. Full Cap'!I6+'B. Two-Sided'!I6+'C. Upside'!I6+'D. REACH'!I6 -> 4807.6881 | J4: ='A. Full Cap'!J6+'B. Two-Sided'!J6+'C. Upside'!J6+'D. REACH'!J6 -> 4856.8667 | ... N4: ='A. Full Cap'!N6+'B. Two-Sided'!N6+'C. Upside'!N6+'D. REACH'!N6 -> 5058.7175 | O4: =SUM(C4:N4) -> 57435.241
A6: REVENUE
A7: Global capitation | C7: ='A. Full Cap'!C15+'B. Two-Sided'!C15+'C. Upside'!C15+'D. REACH'!C15 -> 4759261.9 | D7: ='A. Full Cap'!D15+'B. Two-Sided'!D15+'C. Upside'!D15+'D. REACH'!D15 -> 4806854.5 | E7: ='A. Full Cap'!E15+'B. Two-Sided'!E15+'C. Upside'!E15+'D. REACH'!E15 -> 4854923.1 | F7: ='A. Full Cap'!F15+'B. Two-Sided'!F15+'C. Upside'!F15+'D. REACH'!F15 -> 4903472.3 | G7: ='A. Full Cap'!G15+'B. Two-Sided'!G15+'C. Upside'!G15+'D. REACH'!G15 -> 4952507 | H7: ='A. Full Cap'!H15+'B. Two-Sided'!H15+'C. Upside'!H15+'D. REACH'!H15 -> 5002032.1 | I7: ='A. Full Cap'!I15+'B. Two-Sided'!I15+'C. Upside'!I15+'D. REACH'!I15 -> 5052052.4 | J7: ='A. Full Cap'!J15+'B. Two-Sided'!J15+'C. Upside'!J15+'D. REACH'!J15 -> 5102573 | ... N7: ='A. Full Cap'!N15+'B. Two-Sided'!N15+'C. Upside'!N15+'D. REACH'!N15 -> 5309757.9 | O7: =SUM(C7:N7) -> 60359354
A8: Care management | C8: ='A. Full Cap'!C16+'B. Two-Sided'!C16+'C. Upside'!C16+'D. REACH'!C16 -> 24873.75 | D8: ='A. Full Cap'!D16+'B. Two-Sided'!D16+'C. Upside'!D16+'D. REACH'!D16 -> 25122.487 | E8: ='A. Full Cap'!E16+'B. Two-Sided'!E16+'C. Upside'!E16+'D. REACH'!E16 -> 25373.712 | F8: ='A. Full Cap'!F16+'B. Two-Sided'!F16+'C. Upside'!F16+'D. REACH'!F16 -> 25627.449 | G8: ='A. Full Cap'!G16+'B. Two-Sided'!G16+'C. Upside'!G16+'D. REACH'!G16 -> 25883.724 | H8: ='A. Full Cap'!H16+'B. Two-Sided'!H16+'C. Upside'!H16+'D. REACH'!H16 -> 26142.561 | I8: ='A. Full Cap'!I16+'B. Two-Sided'!I16+'C. Upside'!I16+'D. REACH'!I16 -> 26403.987 | J8: ='A. Full Cap'!J16+'B. Two-Sided'!J16+'C. Upside'!J16+'D. REACH'!J16 -> 26668.027 | ... N8: ='A. Full Cap'!N16+'B. Two-Sided'!N16+'C. Upside'!N16+'D. REACH'!N16 -> 27750.856 | O8: =SUM(C8:N8) -> 315461.41
A9: Primary care cap (PCCP) | C9: ='A. Full Cap'!C17+'B. Two-Sided'!C17+'C. Upside'!C17+'D. REACH'!C17 -> 16120 | D9: ='A. Full Cap'!D17+'B. Two-Sided'!D17+'C. Upside'!D17+'D. REACH'!D17 -> 16361.8 | E9: ='A. Full Cap'!E17+'B. Two-Sided'!E17+'C. Upside'!E17+'D. REACH'!E17 -> 16607.227 | F9: ='A. Full Cap'!F17+'B. Two-Sided'!F17+'C. Upside'!F17+'D. REACH'!F17 -> 16856.335 | G9: ='A. Full Cap'!G17+'B. Two-Sided'!G17+'C. Upside'!G17+'D. REACH'!G17 -> 17109.18 | H9: ='A. Full Cap'!H17+'B. Two-Sided'!H17+'C. Upside'!H17+'D. REACH'!H17 -> 17365.818 | I9: ='A. Full Cap'!I17+'B. Two-Sided'!I17+'C. Upside'!I17+'D. REACH'!I17 -> 17626.305 | J9: ='A. Full Cap'!J17+'B. Two-Sided'!J17+'C. Upside'!J17+'D. REACH'!J17 -> 17890.7 | ... N9: ='A. Full Cap'!N17+'B. Two-Sided'!N17+'C. Upside'!N17+'D. REACH'!N17 -> 18988.537 | O9: =SUM(C9:N9) -> 210224.33
A10: FFS own services | C10: ='A. Full Cap'!C18+'B. Two-Sided'!C18+'C. Upside'!C18+'D. REACH'!C18 -> 12562.5 | D10: ='A. Full Cap'!D18+'B. Two-Sided'!D18+'C. Upside'!D18+'D. REACH'!D18 -> 12688.125 | E10: ='A. Full Cap'!E18+'B. Two-Sided'!E18+'C. Upside'!E18+'D. REACH'!E18 -> 12815.006 | F10: ='A. Full Cap'!F18+'B. Two-Sided'!F18+'C. Upside'!F18+'D. REACH'!F18 -> 12943.156 | G10: ='A. Full Cap'!G18+'B. Two-Sided'!G18+'C. Upside'!G18+'D. REACH'!G18 -> 13072.588 | H10: ='A. Full Cap'!H18+'B. Two-Sided'!H18+'C. Upside'!H18+'D. REACH'!H18 -> 13203.314 | I10: ='A. Full Cap'!I18+'B. Two-Sided'!I18+'C. Upside'!I18+'D. REACH'!I18 -> 13335.347 | J10: ='A. Full Cap'!J18+'B. Two-Sided'!J18+'C. Upside'!J18+'D. REACH'!J18 -> 13468.7 | ... N10: ='A. Full Cap'!N18+'B. Two-Sided'!N18+'C. Upside'!N18+'D. REACH'!N18 -> 14015.584 | O10: =SUM(C10:N10) -> 159323.94
A11: Shared savings / (loss) | C11: ='A. Full Cap'!C22+'B. Two-Sided'!C22+'C. Upside'!C22+'D. REACH'!C22 -> -15156.796 | D11: ='A. Full Cap'!D22+'B. Two-Sided'!D22+'C. Upside'!D22+'D. REACH'!D22 -> -13352.579 | E11: ='A. Full Cap'!E22+'B. Two-Sided'!E22+'C. Upside'!E22+'D. REACH'!E22 -> -11505.142 | F11: ='A. Full Cap'!F22+'B. Two-Sided'!F22+'C. Upside'!F22+'D. REACH'!F22 -> -9613.7026 | G11: ='A. Full Cap'!G22+'B. Two-Sided'!G22+'C. Upside'!G22+'D. REACH'!G22 -> -7677.4662 | H11: ='A. Full Cap'!H22+'B. Two-Sided'!H22+'C. Upside'!H22+'D. REACH'!H22 -> -5695.6238 | I11: ='A. Full Cap'!I22+'B. Two-Sided'!I22+'C. Upside'!I22+'D. REACH'!I22 -> -3667.3535 | J11: ='A. Full Cap'!J22+'B. Two-Sided'!J22+'C. Upside'!J22+'D. REACH'!J22 -> -1591.8196 | ... N11: ='A. Full Cap'!N22+'B. Two-Sided'!N22+'C. Upside'!N22+'D. REACH'!N22 -> 7200.1559 | O11: =SUM(C11:N11) -> -52897.118
A12: Total revenue | C12: =SUM(C7:C11) -> 4797661.4 | D12: =SUM(D7:D11) -> 4847674.4 | E12: =SUM(E7:E11) -> 4898213.9 | F12: =SUM(F7:F11) -> 4949285.6 | G12: =SUM(G7:G11) -> 5000895.1 | H12: =SUM(H7:H11) -> 5053048.2 | I12: =SUM(I7:I11) -> 5105750.7 | J12: =SUM(J7:J11) -> 5159008.6 | ... O12: =SUM(O7:O11) -> 60991466
A14: MEDICAL COST (provider-borne)
A15: Medical claims (full-cap) | C15: ='A. Full Cap'!C26+'B. Two-Sided'!C26+'C. Upside'!C26+'D. REACH'!C26 -> 4371991.2 | D15: ='A. Full Cap'!D26+'B. Two-Sided'!D26+'C. Upside'!D26+'D. REACH'!D26 -> 4392988.8 | E15: ='A. Full Cap'!E26+'B. Two-Sided'!E26+'C. Upside'!E26+'D. REACH'!E26 -> 4413969.1 | F15: ='A. Full Cap'!F26+'B. Two-Sided'!F26+'C. Upside'!F26+'D. REACH'!F26 -> 4434929.7 | G15: ='A. Full Cap'!G26+'B. Two-Sided'!G26+'C. Upside'!G26+'D. REACH'!G26 -> 4455868.1 | H15: ='A. Full Cap'!H26+'B. Two-Sided'!H26+'C. Upside'!H26+'D. REACH'!H26 -> 4476781.8 | I15: ='A. Full Cap'!I26+'B. Two-Sided'!I26+'C. Upside'!I26+'D. REACH'!I26 -> 4497668.2 | J15: ='A. Full Cap'!J26+'B. Two-Sided'!J26+'C. Upside'!J26+'D. REACH'!J26 -> 4518524.7 | ... N15: ='A. Full Cap'!N26+'B. Two-Sided'!N26+'C. Upside'!N26+'D. REACH'!N26 -> 4601596.4 | O15: =SUM(C15:N15) -> 53844690
A16: Stop-loss premium | C16: ='A. Full Cap'!C27+'B. Two-Sided'!C27+'C. Upside'!C27+'D. REACH'!C27 -> 126630 | D16: ='A. Full Cap'!D27+'B. Two-Sided'!D27+'C. Upside'!D27+'D. REACH'!D27 -> 127896.3 | E16: ='A. Full Cap'!E27+'B. Two-Sided'!E27+'C. Upside'!E27+'D. REACH'!E27 -> 129175.26 | F16: ='A. Full Cap'!F27+'B. Two-Sided'!F27+'C. Upside'!F27+'D. REACH'!F27 -> 130467.02 | G16: ='A. Full Cap'!G27+'B. Two-Sided'!G27+'C. Upside'!G27+'D. REACH'!G27 -> 131771.69 | H16: ='A. Full Cap'!H27+'B. Two-Sided'!H27+'C. Upside'!H27+'D. REACH'!H27 -> 133089.4 | I16: ='A. Full Cap'!I27+'B. Two-Sided'!I27+'C. Upside'!I27+'D. REACH'!I27 -> 134420.3 | J16: ='A. Full Cap'!J27+'B. Two-Sided'!J27+'C. Upside'!J27+'D. REACH'!J27 -> 135764.5 | ... N16: ='A. Full Cap'!N27+'B. Two-Sided'!N27+'C. Upside'!N27+'D. REACH'!N27 -> 141277.08 | O16: =SUM(C16:N16) -> 1605985.4
A17: Stop-loss recoveries | C17: ='A. Full Cap'!C28+'B. Two-Sided'!C28+'C. Upside'!C28+'D. REACH'!C28 -> -94068 | D17: ='A. Full Cap'!D28+'B. Two-Sided'!D28+'C. Upside'!D28+'D. REACH'!D28 -> -95008.68 | E17: ='A. Full Cap'!E28+'B. Two-Sided'!E28+'C. Upside'!E28+'D. REACH'!E28 -> -95958.767 | F17: ='A. Full Cap'!F28+'B. Two-Sided'!F28+'C. Upside'!F28+'D. REACH'!F28 -> -96918.354 | G17: ='A. Full Cap'!G28+'B. Two-Sided'!G28+'C. Upside'!G28+'D. REACH'!G28 -> -97887.538 | H17: ='A. Full Cap'!H28+'B. Two-Sided'!H28+'C. Upside'!H28+'D. REACH'!H28 -> -98866.413 | I17: ='A. Full Cap'!I28+'B. Two-Sided'!I28+'C. Upside'!I28+'D. REACH'!I28 -> -99855.078 | J17: ='A. Full Cap'!J28+'B. Two-Sided'!J28+'C. Upside'!J28+'D. REACH'!J28 -> -100853.63 | ... N17: ='A. Full Cap'!N28+'B. Two-Sided'!N28+'C. Upside'!N28+'D. REACH'!N28 -> -104948.69 | O17: =SUM(C17:N17) -> -1193017.7
A18: Total medical cost | C18: =SUM(C15:C17) -> 4404553.2 | D18: =SUM(D15:D17) -> 4425876.4 | E18: =SUM(E15:E17) -> 4447185.6 | F18: =SUM(F15:F17) -> 4468478.3 | G18: =SUM(G15:G17) -> 4489752.3 | H18: =SUM(H15:H17) -> 4511004.8 | I18: =SUM(I15:I17) -> 4532233.4 | J18: =SUM(J15:J17) -> 4553435.5 | ... O18: =SUM(O15:O17) -> 54257658
A20: MEDICAL MARGIN (contribution) | C20: =C12-C18 -> 393108.17 | D20: =D12-D18 -> 421798 | E20: =E12-E18 -> 451028.33 | F20: =F12-F18 -> 480807.21 | G20: =G12-G18 -> 511142.81 | H20: =H12-H18 -> 542043.37 | I20: =I12-I18 -> 573517.28 | J20: =J12-J18 -> 605573.03 | ... O20: =O12-O18 -> 6733808.1
A22: CLINIC OPERATING EXPENSE
A23: Fixed clinic opex | C23: =Assumptions!$B$14 -> 380000 | D23: =Assumptions!$B$14 -> 380000 | E23: =Assumptions!$B$14 -> 380000 | F23: =Assumptions!$B$14 -> 380000 | G23: =Assumptions!$B$14 -> 380000 | H23: =Assumptions!$B$14 -> 380000 | I23: =Assumptions!$B$14 -> 380000 | J23: =Assumptions!$B$14 -> 380000 | ... N23: =Assumptions!$B$14 -> 380000 | O23: =SUM(C23:N23) -> 4560000
A24: Care management (variable) | C24: =C4*Assumptions!$B$15 -> 81414 | D24: =D4*Assumptions!$B$15 -> 82246.275 | E24: =E4*Assumptions!$B$15 -> 83087.145 | F24: =F4*Assumptions!$B$15 -> 83936.699 | G24: =G4*Assumptions!$B$15 -> 84795.03 | H24: =H4*Assumptions!$B$15 -> 85662.228 | I24: =I4*Assumptions!$B$15 -> 86538.387 | J24: =J4*Assumptions!$B$15 -> 87423.6 | ... N24: =N4*Assumptions!$B$15 -> 91056.914 | O24: =SUM(C24:N24) -> 1033834.3
A25: G&A / corporate | C25: =Assumptions!$B$16 -> 120000 | D25: =Assumptions!$B$16 -> 120000 | E25: =Assumptions!$B$16 -> 120000 | F25: =Assumptions!$B$16 -> 120000 | G25: =Assumptions!$B$16 -> 120000 | H25: =Assumptions!$B$16 -> 120000 | I25: =Assumptions!$B$16 -> 120000 | J25: =Assumptions!$B$16 -> 120000 | ... N25: =Assumptions!$B$16 -> 120000 | O25: =SUM(C25:N25) -> 1440000
A26: Total clinic opex | C26: =SUM(C23:C25) -> 581414 | D26: =SUM(D23:D25) -> 582246.28 | E26: =SUM(E23:E25) -> 583087.14 | F26: =SUM(F23:F25) -> 583936.7 | G26: =SUM(G23:G25) -> 584795.03 | H26: =SUM(H23:H25) -> 585662.23 | I26: =SUM(I23:I25) -> 586538.39 | J26: =SUM(J23:J25) -> 587423.6 | ... O26: =SUM(O23:O25) -> 7033834.3
A28: EBITDA | C28: =C20-C26 -> -188305.83 | D28: =D20-D26 -> -160448.28 | E28: =E20-E26 -> -132058.82 | F28: =F20-F26 -> -103129.49 | G28: =G20-G26 -> -73652.224 | H28: =H20-H26 -> -43618.857 | I28: =I20-I26 -> -13021.102 | J28: =J20-J26 -> 18149.434 | ... O28: =O20-O26 -> -300026.21
A29: EBITDA margin | C29: =IF(C12=0,0,C28/C12) -> -0.039249503 | D29: =IF(D12=0,0,D28/D12) -> -0.03309799 | E29: =IF(E12=0,0,E28/E12) -> -0.026960606 | F29: =IF(F12=0,0,F28/F12) -> -0.020837247 | G29: =IF(G12=0,0,G28/G12) -> -0.014727808 | H29: =IF(H12=0,0,H28/H12) -> -0.008632187 | I29: =IF(I12=0,0,I28/I12) -> -0.0025502817 | J29: =IF(J12=0,0,J28/J12) -> 0.0035180082 | ... O29: =IF(O12=0,0,O28/O12) -> -0.0049191506
A30: Medical margin PMPM | C30: =IF(C4=0,0,C20/C4) -> 86.913149 | D30: =IF(D4=0,0,D20/D4) -> 92.312557 | E30: =IF(E4=0,0,E20/E4) -> 97.710782 | F30: =IF(F4=0,0,F20/F4) -> 103.10782 | G30: =IF(G4=0,0,G20/G4) -> 108.50365 | H30: =IF(H4=0,0,H20/H4) -> 113.89828 | I30: =IF(I4=0,0,I20/I4) -> 119.2917 | J30: =IF(J4=0,0,J20/J4) -> 124.68389 | ... O30: =IF(O4=0,0,O20/O4) -> 117.24175

Sheet Cash Flow
A1: CASH FLOW — Year 1 (Monthly)
A2: Full-cap dynamic: capitation received prospectively, claims paid in arrears (lag), IBNR float builds.
C3: Jan | D3: Feb | E3: Mar | F3: Apr | G3: May | H3: Jun | I3: Jul | J3: Aug | K3: Sep | L3: Oct | M3: Nov | N3: Dec | O3: Year 1
A4: OPERATING CASH IN
A5: Capitation & fees received (prospective) | C5: ='P&L (Monthly)'!C7+'P&L (Monthly)'!C8+'P&L (Monthly)'!C9+'P&L (Monthly)'!C10 -> 4812818.2 | D5: ='P&L (Monthly)'!D7+'P&L (Monthly)'!D8+'P&L (Monthly)'!D9+'P&L (Monthly)'!D10 -> 4861027 | E5: ='P&L (Monthly)'!E7+'P&L (Monthly)'!E8+'P&L (Monthly)'!E9+'P&L (Monthly)'!E10 -> 4909719 | F5: ='P&L (Monthly)'!F7+'P&L (Monthly)'!F8+'P&L (Monthly)'!F9+'P&L (Monthly)'!F10 -> 4958899.3 | G5: ='P&L (Monthly)'!G7+'P&L (Monthly)'!G8+'P&L (Monthly)'!G9+'P&L (Monthly)'!G10 -> 5008572.5 | H5: ='P&L (Monthly)'!H7+'P&L (Monthly)'!H8+'P&L (Monthly)'!H9+'P&L (Monthly)'!H10 -> 5058743.8 | I5: ='P&L (Monthly)'!I7+'P&L (Monthly)'!I8+'P&L (Monthly)'!I9+'P&L (Monthly)'!I10 -> 5109418.1 | J5: ='P&L (Monthly)'!J7+'P&L (Monthly)'!J8+'P&L (Monthly)'!J9+'P&L (Monthly)'!J10 -> 5160600.4 | ... N5: ='P&L (Monthly)'!N7+'P&L (Monthly)'!N8+'P&L (Monthly)'!N9+'P&L (Monthly)'!N10 -> 5370512.9 | O5: =SUM(C5:N5) -> 61044363
A6: Settlement received (prior-yr true-up) | C6: 0 | D6: 0 | E6: 0 | F6: 0 | G6: 0 | H6: 0 | I6: 0 | J6: 0 | K6: 0 | L6: 0 | M6: 0 | N6: 0 | O6: =SUM(C6:N6) -> 0
A7: Total cash in | C7: =C5+C6 -> 4812818.2 | D7: =D5+D6 -> 4861027 | E7: =E5+E6 -> 4909719 | F7: =F5+F6 -> 4958899.3 | G7: =G5+G6 -> 5008572.5 | H7: =H5+H6 -> 5058743.8 | I7: =I5+I6 -> 5109418.1 | J7: =J5+J6 -> 5160600.4 | ... N7: =N5+N6 -> 5370512.9 | O7: =SUM(C7:N7) -> 61044363
A9: OPERATING CASH OUT
A10: Medical claims paid (2-mo lag) | C10: =0 -> 0 | D10: =0 -> 0 | E10: ='P&L (Monthly)'!C15 -> 4371991.2 | F10: ='P&L (Monthly)'!D15 -> 4392988.8 | G10: ='P&L (Monthly)'!E15 -> 4413969.1 | H10: ='P&L (Monthly)'!F15 -> 4434929.7 | I10: ='P&L (Monthly)'!G15 -> 4455868.1 | J10: ='P&L (Monthly)'!H15 -> 4476781.8 | K10: ='P&L (Monthly)'!I15 -> 4497668.2 | L10: ='P&L (Monthly)'!J15 -> 4518524.7 | ... N10: ='P&L (Monthly)'!L15 -> 4560136.9 | O10: =SUM(C10:N10) -> 44662207
A11: Stop-loss premium paid | C11: ='P&L (Monthly)'!C16 -> 126630 | D11: ='P&L (Monthly)'!D16 -> 127896.3 | E11: ='P&L (Monthly)'!E16 -> 129175.26 | F11: ='P&L (Monthly)'!F16 -> 130467.02 | G11: ='P&L (Monthly)'!G16 -> 131771.69 | H11: ='P&L (Monthly)'!H16 -> 133089.4 | I11: ='P&L (Monthly)'!I16 -> 134420.3 | J11: ='P&L (Monthly)'!J16 -> 135764.5 | ... N11: ='P&L (Monthly)'!N16 -> 141277.08 | O11: =SUM(C11:N11) -> 1605985.4
A12: Clinic operating expense paid | C12: ='P&L (Monthly)'!C26 -> 581414 | D12: ='P&L (Monthly)'!D26 -> 582246.28 | E12: ='P&L (Monthly)'!E26 -> 583087.14 | F12: ='P&L (Monthly)'!F26 -> 583936.7 | G12: ='P&L (Monthly)'!G26 -> 584795.03 | H12: ='P&L (Monthly)'!H26 -> 585662.23 | I12: ='P&L (Monthly)'!I26 -> 586538.39 | J12: ='P&L (Monthly)'!J26 -> 587423.6 | ... N12: ='P&L (Monthly)'!N26 -> 591056.91 | O12: =SUM(C12:N12) -> 7033834.3
A13: Total cash out | C13: =C10+C11+C12 -> 708044 | D13: =D10+D11+D12 -> 710142.57 | E13: =E10+E11+E12 -> 5084253.6 | F13: =F10+F11+F12 -> 5107392.5 | G13: =G10+G11+G12 -> 5130535.8 | H13: =H10+H11+H12 -> 5153681.3 | I13: =I10+I11+I12 -> 5176826.8 | J13: =J10+J11+J12 -> 5199969.9 | ... N13: =N10+N11+N12 -> 5292470.9 | O13: =SUM(C13:N13) -> 53302027
A15: NET OPERATING CASH FLOW | C15: =C7-C13 -> 4104774.2 | D15: =D7-D13 -> 4150884.4 | E15: =E7-E13 -> -174534.58 | F15: =F7-F13 -> -148493.21 | G15: =G7-G13 -> -121963.25 | H15: =H7-H13 -> -94937.509 | I15: =I7-I13 -> -67408.726 | J15: =J7-J13 -> -39369.537 | ... N15: =N7-N13 -> 78041.965 | O15: =SUM(C15:N15) -> 7742336.8
A16: Cumulative cash position | C16: =C15 -> 4104774.2 | D16: =C16+D15 -> 8255658.5 | E16: =D16+E15 -> 8081124 | F16: =E16+F15 -> 7932630.8 | G16: =F16+G15 -> 7810667.5 | H16: =G16+H15 -> 7715730 | I16: =H16+I15 -> 7648321.3 | J16: =I16+J15 -> 7608951.7 | K16: =J16+K15 -> 7598139.3 | ... N16: =M16+N15 -> 7742336.8 | O16: =N16 -> 7742336.8
A18: CLAIMS PAYABLE / IBNR FLOAT (full-cap)
A19: Claims incurred | C19: ='P&L (Monthly)'!C15 -> 4371991.2 | D19: ='P&L (Monthly)'!D15 -> 4392988.8 | E19: ='P&L (Monthly)'!E15 -> 4413969.1 | F19: ='P&L (Monthly)'!F15 -> 4434929.7 | G19: ='P&L (Monthly)'!G15 -> 4455868.1 | H19: ='P&L (Monthly)'!H15 -> 4476781.8 | I19: ='P&L (Monthly)'!I15 -> 4497668.2 | J19: ='P&L (Monthly)'!J15 -> 4518524.7 | ... N19: ='P&L (Monthly)'!N15 -> 4601596.4
A20: Claims paid | C20: =C10 -> 0 | D20: =D10 -> 0 | E20: =E10 -> 4371991.2 | F20: =F10 -> 4392988.8 | G20: =G10 -> 4413969.1 | H20: =H10 -> 4434929.7 | I20: =I10 -> 4455868.1 | J20: =J10 -> 4476781.8 | ... N20: =N10 -> 4560136.9
A21: Ending claims payable (IBNR + unpaid) | C21: =C19-C20 -> 4371991.2 | D21: =C21+D19-D20 -> 8764980 | E21: =D21+E19-E20 -> 8806957.8 | F21: =E21+F19-F20 -> 8848898.7 | G21: =F21+G19-G20 -> 8890797.8 | H21: =G21+H19-H20 -> 8932649.9 | I21: =H21+I19-I20 -> 8974450 | J21: =I21+J19-J20 -> 9016192.9 | K21: =J21+K19-K20 -> 9057873.1 | ... N21: =M21+N19-N20 -> 9182483.6

Sheet 3-Yr & Cohorts
A1: 3-YEAR SUMMARY & COHORT J-CURVE
A3: CONTRIBUTION PMPM BY CONTRACT × TENURE (Year-1 $, isolates maturation)
A4: Contract | B4: Tenure Yr 1 | C4: Tenure Yr 2 | D4: Tenure Yr 3
A5: A · Full Cap | B5: =(Assumptions!$B$37*(Assumptions!$B$36*Assumptions!$B$52)*Assumptions!$B$38)+(Assumptions!$B$39+Assumptions!$B$40+Assumptions!$B$41)+IF(Assumptions!$B$33=1,0,IF(((Assumptions!$B$37*(Assumptions!$B$36*Assumptions!$B$52)*Assumptions!$B$42)-(Assumptions!$B$46*Assumptions!$C$52))>=0,((Assumptions!$B$37*(Assumptions!$B$36*Assumptions!$B$52)*Assumptions!$B$42)-(Assumptions!$B$46*Assumptions!$C$52))*Assumptions!$B$43,((Assumptions!$B$37*(Assumptions!$B$36*Assumptions!$B$52)*Assumptions!$B$42)-(Assumptions!$B$46*Assumptions!$C$52))*Assumptions!$B$44*Assumptions!$B$45))-(Assumptions!$B$33*(Assumptions!$B$46*Assumptions!$C$52))-(Assumptions!$B$33*(Assumptions!$B$47-Assumptions!$B$48)) -> 98.04 | C5: =(Assumptions!$B$37*(Assumptions!$B$36*Assumptions!$B$53)*Assumptions!$B$38)+(Assumptions!$B$39+Assumptions!$B$40+Assumptions!$B$41)+IF(Assumptions!$B$33=1,0,IF(((Assumptions!$B$37*(Assumptions!$B$36*Assumptions!$B$53)*Assumptions!$B$42)-(Assumptions!$B$46*Assumptions!$C$53))>=0,((Assumptions!$B$37*(Assumptions!$B$36*Assumptions!$B$53)*Assumptions!$B$42)-(Assumptions!$B$46*Assumptions!$C$53))*Assumptions!$B$43,((Assumptions!$B$37*(Assumptions!$B$36*Assumptions!$B$53)*Assumptions!$B$42)-(Assumptions!$B$46*Assumptions!$C$53))*Assumptions!$B$44*Assumptions!$B$45))-(Assumptions!$B$33*(Assumptions!$B$46*Assumptions!$C$53))-(Assumptions!$B$33*(Assumptions!$B$47-Assumptions!$B$48)) -> 260.568 | D5: =(Assumptions!$B$37*(Assumptions!$B$36*Assumptions!$B$54)*Assumptions!$B$38)+(Assumptions!$B$39+Assumptions!$B$40+Assumptions!$B$41)+IF(Assumptions!$B$33=1,0,IF(((Assumptions!$B$37*(Assumptions!$B$36*Assumptions!$B$54)*Assumptions!$B$42)-(Assumptions!$B$46*Assumptions!$C$54))>=0,((Assumptions!$B$37*(Assumptions!$B$36*Assumptions!$B$54)*Assumptions!$B$42)-(Assumptions!$B$46*Assumptions!$C$54))*Assumptions!$B$43,((Assumptions!$B$37*(Assumptions!$B$36*Assumptions!$B$54)*Assumptions!$B$42)-(Assumptions!$B$46*Assumptions!$C$54))*Assumptions!$B$44*Assumptions!$B$45))-(Assumptions!$B$33*(Assumptions!$B$46*Assumptions!$C$54))-(Assumptions!$B$33*(Assumptions!$B$47-Assumptions!$B$48)) -> 312.6
A6: B · Two-Sided | B6: =(Assumptions!$C$37*(Assumptions!$C$36*Assumptions!$B$52)*Assumptions!$C$38)+(Assumptions!$C$39+Assumptions!$C$40+Assumptions!$C$41)+IF(Assumptions!$C$33=1,0,IF(((Assumptions!$C$37*(Assumptions!$C$36*Assumptions!$B$52)*Assumptions!$C$42)-(Assumptions!$C$46*Assumptions!$C$52))>=0,((Assumptions!$C$37*(Assumptions!$C$36*Assumptions!$B$52)*Assumptions!$C$42)-(Assumptions!$C$46*Assumptions!$C$52))*Assumptions!$C$43,((Assumptions!$C$37*(Assumptions!$C$36*Assumptions!$B$52)*Assumptions!$C$42)-(Assumptions!$C$46*Assumptions!$C$52))*Assumptions!$C$44*Assumptions!$C$45))-(Assumptions!$C$33*(Assumptions!$C$46*Assumptions!$C$52))-(Assumptions!$C$33*(Assumptions!$C$47-Assumptions!$C$48)) -> 22.73 | C6: =(Assumptions!$C$37*(Assumptions!$C$36*Assumptions!$B$53)*Assumptions!$C$38)+(Assumptions!$C$39+Assumptions!$C$40+Assumptions!$C$41)+IF(Assumptions!$C$33=1,0,IF(((Assumptions!$C$37*(Assumptions!$C$36*Assumptions!$B$53)*Assumptions!$C$42)-(Assumptions!$C$46*Assumptions!$C$53))>=0,((Assumptions!$C$37*(Assumptions!$C$36*Assumptions!$B$53)*Assumptions!$C$42)-(Assumptions!$C$46*Assumptions!$C$53))*Assumptions!$C$43,((Assumptions!$C$37*(Assumptions!$C$36*Assumptions!$B$53)*Assumptions!$C$42)-(Assumptions!$C$46*Assumptions!$C$53))*Assumptions!$C$44*Assumptions!$C$45))-(Assumptions!$C$33*(Assumptions!$C$46*Assumptions!$C$53))-(Assumptions!$C$33*(Assumptions!$C$47-Assumptions!$C$48)) -> 95.026 | D6: =(Assumptions!$C$37*(Assumptions!$C$36*Assumptions!$B$54)*Assumptions!$C$38)+(Assumptions!$C$39+Assumptions!$C$40+Assumptions!$C$41)+IF(Assumptions!$C$33=1,0,IF(((Assumptions!$C$37*(Assumptions!$C$36*Assumptions!$B$54)*Assumptions!$C$42)-(Assumptions!$C$46*Assumptions!$C$54))>=0,((Assumptions!$C$37*(Assumptions!$C$36*Assumptions!$B$54)*Assumptions!$C$42)-(Assumptions!$C$46*Assumptions!$C$54))*Assumptions!$C$43,((Assumptions!$C$37*(Assumptions!$C$36*Assumptions!$B$54)*Assumptions!$C$42)-(Assumptions!$C$46*Assumptions!$C$54))*Assumptions!$C$44*Assumptions!$C$45))-(Assumptions!$C$33*(Assumptions!$C$46*Assumptions!$C$54))-(Assumptions!$C$33*(Assumptions!$C$47-Assumptions!$C$48)) -> 118.7
A7: C · Upside | B7: =(Assumptions!$D$37*(Assumptions!$D$36*Assumptions!$B$52)*Assumptions!$D$38)+(Assumptions!$D$39+Assumptions!$D$40+Assumptions!$D$41)+IF(Assumptions!$D$33=1,0,IF(((Assumptions!$D$37*(Assumptions!$D$36*Assumptions!$B$52)*Assumptions!$D$42)-(Assumptions!$D$46*Assumptions!$C$52))>=0,((Assumptions!$D$37*(Assumptions!$D$36*Assumptions!$B$52)*Assumptions!$D$42)-(Assumptions!$D$46*Assumptions!$C$52))*Assumptions!$D$43,((Assumptions!$D$37*(Assumptions!$D$36*Assumptions!$B$52)*Assumptions!$D$42)-(Assumptions!$D$46*Assumptions!$C$52))*Assumptions!$D$44*Assumptions!$D$45))-(Assumptions!$D$33*(Assumptions!$D$46*Assumptions!$C$52))-(Assumptions!$D$33*(Assumptions!$D$47-Assumptions!$D$48)) -> 50 | C7: =(Assumptions!$D$37*(Assumptions!$D$36*Assumptions!$B$53)*Assumptions!$D$38)+(Assumptions!$D$39+Assumptions!$D$40+Assumptions!$D$41)+IF(Assumptions!$D$33=1,0,IF(((Assumptions!$D$37*(Assumptions!$D$36*Assumptions!$B$53)*Assumptions!$D$42)-(Assumptions!$D$46*Assumptions!$C$53))>=0,((Assumptions!$D$37*(Assumptions!$D$36*Assumptions!$B$53)*Assumptions!$D$42)-(Assumptions!$D$46*Assumptions!$C$53))*Assumptions!$D$43,((Assumptions!$D$37*(Assumptions!$D$36*Assumptions!$B$53)*Assumptions!$D$42)-(Assumptions!$D$46*Assumptions!$C$53))*Assumptions!$D$44*Assumptions!$D$45))-(Assumptions!$D$33*(Assumptions!$D$46*Assumptions!$C$53))-(Assumptions!$D$33*(Assumptions!$D$47-Assumptions!$D$48)) -> 62.78 | D7: =(Assumptions!$D$37*(Assumptions!$D$36*Assumptions!$B$54)*Assumptions!$D$38)+(Assumptions!$D$39+Assumptions!$D$40+Assumptions!$D$41)+IF(Assumptions!$D$33=1,0,IF(((Assumptions!$D$37*(Assumptions!$D$36*Assumptions!$B$54)*Assumptions!$D$42)-(Assumptions!$D$46*Assumptions!$C$54))>=0,((Assumptions!$D$37*(Assumptions!$D$36*Assumptions!$B$54)*Assumptions!$D$42)-(Assumptions!$D$46*Assumptions!$C$54))*Assumptions!$D$43,((Assumptions!$D$37*(Assumptions!$D$36*Assumptions!$B$54)*Assumptions!$D$42)-(Assumptions!$D$46*Assumptions!$C$54))*Assumptions!$D$44*Assumptions!$D$45))-(Assumptions!$D$33*(Assumptions!$D$46*Assumptions!$C$54))-(Assumptions!$D$33*(Assumptions!$D$47-Assumptions!$D$48)) -> 89
A8: D · REACH | B8: =(Assumptions!$E$37*(Assumptions!$E$36*Assumptions!$B$52)*Assumptions!$E$38)+(Assumptions!$E$39+Assumptions!$E$40+Assumptions!$E$41)+IF(Assumptions!$E$33=1,0,IF(((Assumptions!$E$37*(Assumptions!$E$36*Assumptions!$B$52)*Assumptions!$E$42)-(Assumptions!$E$46*Assumptions!$C$52))>=0,((Assumptions!$E$37*(Assumptions!$E$36*Assumptions!$B$52)*Assumptions!$E$42)-(Assumptions!$E$46*Assumptions!$C$52))*Assumptions!$E$43,((Assumptions!$E$37*(Assumptions!$E$36*Assumptions!$B$52)*Assumptions!$E$42)-(Assumptions!$E$46*Assumptions!$C$52))*Assumptions!$E$44*Assumptions!$E$45))-(Assumptions!$E$33*(Assumptions!$E$46*Assumptions!$C$52))-(Assumptions!$E$33*(Assumptions!$E$47-Assumptions!$E$48)) -> 77.2075 | C8: =(Assumptions!$E$37*(Assumptions!$E$36*Assumptions!$B$53)*Assumptions!$E$38)+(Assumptions!$E$39+Assumptions!$E$40+Assumptions!$E$41)+IF(Assumptions!$E$33=1,0,IF(((Assumptions!$E$37*(Assumptions!$E$36*Assumptions!$B$53)*Assumptions!$E$42)-(Assumptions!$E$46*Assumptions!$C$53))>=0,((Assumptions!$E$37*(Assumptions!$E$36*Assumptions!$B$53)*Assumptions!$E$42)-(Assumptions!$E$46*Assumptions!$C$53))*Assumptions!$E$43,((Assumptions!$E$37*(Assumptions!$E$36*Assumptions!$B$53)*Assumptions!$E$42)-(Assumptions!$E$46*Assumptions!$C$53))*Assumptions!$E$44*Assumptions!$E$45))-(Assumptions!$E$33*(Assumptions!$E$46*Assumptions!$C$53))-(Assumptions!$E$33*(Assumptions!$E$47-Assumptions!$E$48)) -> 144.7415 | D8: =(Assumptions!$E$37*(Assumptions!$E$36*Assumptions!$B$54)*Assumptions!$E$38)+(Assumptions!$E$39+Assumptions!$E$40+Assumptions!$E$41)+IF(Assumptions!$E$33=1,0,IF(((Assumptions!$E$37*(Assumptions!$E$36*Assumptions!$B$54)*Assumptions!$E$42)-(Assumptions!$E$46*Assumptions!$C$54))>=0,((Assumptions!$E$37*(Assumptions!$E$36*Assumptions!$B$54)*Assumptions!$E$42)-(Assumptions!$E$46*Assumptions!$C$54))*Assumptions!$E$43,((Assumptions!$E$37*(Assumptions!$E$36*Assumptions!$B$54)*Assumptions!$E$42)-(Assumptions!$E$46*Assumptions!$C$54))*Assumptions!$E$44*Assumptions!$E$45))-(Assumptions!$E$33*(Assumptions!$E$46*Assumptions!$C$54))-(Assumptions!$E$33*(Assumptions!$E$47-Assumptions!$E$48)) -> 166.675
A9: Blended (weighted by members) | B9: =(B5*Assumptions!$B$34+B6*Assumptions!$C$34+B7*Assumptions!$D$34+B8*Assumptions!$E$34)/(Assumptions!$B$34+Assumptions!$C$34+Assumptions!$D$34+Assumptions!$E$34) -> 86.914222 | C9: =(C5*Assumptions!$B$34+C6*Assumptions!$C$34+C7*Assumptions!$D$34+C8*Assumptions!$E$34)/(Assumptions!$B$34+Assumptions!$C$34+Assumptions!$D$34+Assumptions!$E$34) -> 227.87773 | D9: =(D5*Assumptions!$B$34+D6*Assumptions!$C$34+D7*Assumptions!$D$34+D8*Assumptions!$E$34)/(Assumptions!$B$34+Assumptions!$C$34+Assumptions!$D$34+Assumptions!$E$34) -> 274.30222
A11: ENROLLMENT COHORTS (members)
B12: Year 1 | C12: Year 2 | D12: Year 3
A13: Cohort 1 (Yr-1 enrollees) | B13: =Assumptions!$B$58 -> 4500 | C13: =B13*Assumptions!$B$59 -> 4050 | D13: =C13*Assumptions!$B$59 -> 3645
A14: Cohort 2 (Yr-2 enrollees) | B14: 0 | C14: =Assumptions!$C$58 -> 900 | D14: =C14*Assumptions!$B$59 -> 810
A15: Cohort 3 (Yr-3 enrollees) | B15: 0 | C15: 0 | D15: =Assumptions!$D$58 -> 800
A16: Total members (avg) | B16: =SUM(B13:B15) -> 4500 | C16: =SUM(C13:C15) -> 4950 | D16: =SUM(D13:D15) -> 5255
A18: ANNUAL P&L (cohort-weighted; price/cost trend held flat for clarity)
B19: Year 1 | C19: Year 2 | D19: Year 3
A20: Member-months | B20: ='P&L (Monthly)'!O4 -> 57435.241 | C20: =C16*12 -> 59400 | D20: =D16*12 -> 63060
A21: Blended medical margin PMPM | B21: ='P&L (Monthly)'!O20/'P&L (Monthly)'!O4 -> 117.24175 | C21: =(C13*C9+C14*B9)/C16+('P&L (Monthly)'!O20/'P&L (Monthly)'!O4-B9) -> 232.57553 | D21: =(D13*D9+D14*C9+D15*B9)/D16+('P&L (Monthly)'!O20/'P&L (Monthly)'!O4-B9) -> 268.94674
A22: Medical margin ($) | B22: ='P&L (Monthly)'!O20 -> 6733808.1 | C22: =C21*C20 -> 13814987 | D22: =D21*D20 -> 16959781
A23: Clinic opex ($) | B23: ='P&L (Monthly)'!O26 -> 7033834.3 | C23: =(Assumptions!$B$14+Assumptions!$B$16)*12+C20*Assumptions!$B$15 -> 7069200 | D23: =(Assumptions!$B$14+Assumptions!$B$16)*12+D20*Assumptions!$B$15 -> 7135080
A24: EBITDA ($) | B24: ='P&L (Monthly)'!O28 -> -300026.21 | C24: =C22-C23 -> 6745786.6 | D24: =D22-D23 -> 9824701.2
A25: EBITDA margin (% of med margin) | B25: =IF(B22=0,0,B24/B22) -> -0.044555206 | C25: =IF(C22=0,0,C24/C22) -> 0.48829483 | D25: =IF(D22=0,0,D24/D22) -> 0.5792941
A27: J-curve: margin PMPM rises as RAF is recaptured (risk lever) and utilization falls with engagement (TCOC lever);
A28: scaling membership on a maturing panel drives the clinic from EBITDA loss to profit.

Sheet KPIs
A1: KPI DASHBOARD — by contract (Year 1)
A3: PER-CONTRACT METRICS
A4: Metric | B4: A · Full Cap | C4: B · Two-Sided | D4: C · Upside | E4: D · REACH | F4: Blended
A5: Avg members (Year 1) | B5: ='A. Full Cap'!O5 -> 4056.5701 | C5: ='B. Two-Sided'!O5 -> 507.07126 | D5: ='C. Upside'!O5 -> 281.70626 | E5: ='D. REACH'!O5 -> 239.12363 | F5: =SUM(B5:E5) -> 5084.4713
A6: Mature RAF | B6: =Assumptions!B36 -> 1.12 | C6: =Assumptions!C36 -> 1.05 | D6: =Assumptions!D36 -> 1 | E6: =Assumptions!E36 -> 1.05
A7: RAF (Yr-1 cohort) | B7: ='A. Full Cap'!C9 -> 1.008 | C7: ='B. Two-Sided'!C9 -> 0.945 | D7: ='C. Upside'!C9 -> 0.9 | E7: ='D. REACH'!C9 -> 0.945
A8: Total revenue ($) | B8: ='A. Full Cap'!O23 -> 60359354 | C8: ='B. Two-Sided'!O23 -> 228807.63 | D8: ='C. Upside'!O23 -> 159323.94 | E8: ='D. REACH'!O23 -> 243980.99 | F8: =SUM(B8:E8) -> 60991466
A9: Medical loss ratio (MLR) | B9: ='A. Full Cap'!O33 -> 0.80286183 | C9: ='B. Two-Sided'!O33 -> 0.90368473 | D9: ='C. Upside'!O33 -> 0.96987963 | E9: ='D. REACH'!O33 -> 0.95635895
A10: Contribution margin ($) | B10: ='A. Full Cap'!O32 -> 6101695.6 | C10: ='B. Two-Sided'!O32 -> 228807.63 | D10: ='C. Upside'!O32 -> 159323.94 | E10: ='D. REACH'!O32 -> 243980.99 | F10: =SUM(B10:E10) -> 6733808.1
A11: Contribution PMPM | B11: ='A. Full Cap'!O34 -> 132.97714 | C11: ='B. Two-Sided'!O34 -> 39.892105 | D11: ='C. Upside'!O34 -> 50 | E11: ='D. REACH'!O34 -> 92.845957
A12: Inpatient admits / 1,000 (assumed) | B12: =Assumptions!$B$11 -> 185 | C12: =Assumptions!$B$11 -> 185 | D12: =Assumptions!$B$11 -> 185 | E12: =Assumptions!$B$11 -> 185
A13: Inpatient TCOC PMPM | B13: =Assumptions!B46*Assumptions!$B$19 -> 342 | C13: =Assumptions!C46*Assumptions!$B$19 -> 336 | D13: =Assumptions!D46*Assumptions!$B$19 -> 318 | E13: =Assumptions!E46*Assumptions!$B$19 -> 303
A15: MLR = actual TCOC / risk-adjusted premium. Contribution = provider revenue less provider-borne medical cost (pre-clinic-opex).

Sheet A · Cash Structures
A1: CONTRACT A - Two Operating Structures for Global Cap
A2: Identical economics, different cash timing: who pays claims and who holds the IBNR float.
C3: Jan | D3: Feb | E3: Mar | F3: Apr | G3: May | H3: Jun | I3: Jul | J3: Aug | K3: Sep | L3: Oct | M3: Nov | N3: Dec | O3: Year 1
A5: SCENARIO INPUTS
A6: Care-management PMPM (plan-pays case) | B6: 45
A7: Settlement lag (months) - true-up paid next year | B7: 9
A9: ECONOMIC RESULT (identical under both structures)
A10: Global cap earned | C10: ='A. Full Cap'!C15 -> 4759261.9 | D10: ='A. Full Cap'!D15 -> 4806854.5 | E10: ='A. Full Cap'!E15 -> 4854923.1 | F10: ='A. Full Cap'!F15 -> 4903472.3 | G10: ='A. Full Cap'!G15 -> 4952507 | H10: ='A. Full Cap'!H15 -> 5002032.1 | I10: ='A. Full Cap'!I15 -> 5052052.4 | J10: ='A. Full Cap'!J15 -> 5102573 | ... N10: ='A. Full Cap'!N15 -> 5309757.9 | O10: =SUM(C10:N10) -> 60359354
A11: Claims incurred | C11: ='A. Full Cap'!C20 -> 4371991.2 | D11: ='A. Full Cap'!D20 -> 4392988.8 | E11: ='A. Full Cap'!E20 -> 4413969.1 | F11: ='A. Full Cap'!F20 -> 4434929.7 | G11: ='A. Full Cap'!G20 -> 4455868.1 | H11: ='A. Full Cap'!H20 -> 4476781.8 | I11: ='A. Full Cap'!I20 -> 4497668.2 | J11: ='A. Full Cap'!J20 -> 4518524.7 | ... N11: ='A. Full Cap'!N20 -> 4601596.4 | O11: =SUM(C11:N11) -> 53844690
A12: Stop-loss premium | C12: ='A. Full Cap'!C27 -> 126630 | D12: ='A. Full Cap'!D27 -> 127896.3 | E12: ='A. Full Cap'!E27 -> 129175.26 | F12: ='A. Full Cap'!F27 -> 130467.02 | G12: ='A. Full Cap'!G27 -> 131771.69 | H12: ='A. Full Cap'!H27 -> 133089.4 | I12: ='A. Full Cap'!I27 -> 134420.3 | J12: ='A. Full Cap'!J27 -> 135764.5 | ... N12: ='A. Full Cap'!N27 -> 141277.08 | O12: =SUM(C12:N12) -> 1605985.4
A13: Stop-loss recoveries | C13: =-'A. Full Cap'!C28 -> 94068 | D13: =-'A. Full Cap'!D28 -> 95008.68 | E13: =-'A. Full Cap'!E28 -> 95958.767 | F13: =-'A. Full Cap'!F28 -> 96918.354 | G13: =-'A. Full Cap'!G28 -> 97887.538 | H13: =-'A. Full Cap'!H28 -> 98866.413 | I13: =-'A. Full Cap'!I28 -> 99855.078 | J13: =-'A. Full Cap'!J28 -> 100853.63 | ... N13: =-'A. Full Cap'!N28 -> 104948.69 | O13: =SUM(C13:N13) -> 1193017.7
A14: Net economic margin | C14: =C10-C11-C12+C13 -> 354708.72 | D14: =D10-D11-D12+D13 -> 380978.16 | E14: =E10-E11-E12+E13 -> 407737.52 | F14: =F10-F11-F12+F13 -> 434993.97 | G14: =G10-G11-G12+G13 -> 462754.78 | H14: =H10-H11-H12+H13 -> 491027.3 | I14: =I10-I11-I12+I13 -> 519819 | J14: =J10-J11-J12+J13 -> 549137.43 | ... N14: =N10-N11-N12+N13 -> 671833.08 | O14: =SUM(C14:N14) -> 6101695.6
A16: STRUCTURE 1 - DELEGATED (provider adjudicates & pays claims)
A17: Cash in: full capitation received | C17: =C10 -> 4759261.9 | D17: =D10 -> 4806854.5 | E17: =E10 -> 4854923.1 | F17: =F10 -> 4903472.3 | G17: =G10 -> 4952507 | H17: =H10 -> 5002032.1 | I17: =I10 -> 5052052.4 | J17: =J10 -> 5102573 | ... N17: =N10 -> 5309757.9 | O17: =SUM(C17:N17) -> 60359354
A18: Cash out: claims paid (2-mo lag) | C18: =0 -> 0 | D18: =0 -> 0 | E18: =-C11 -> -4371991.2 | F18: =-D11 -> -4392988.8 | G18: =-E11 -> -4413969.1 | H18: =-F11 -> -4434929.7 | I18: =-G11 -> -4455868.1 | J18: =-H11 -> -4476781.8 | K18: =-I11 -> -4497668.2 | L18: =-J11 -> -4518524.7 | ... N18: =-L11 -> -4560136.9 | O18: =SUM(C18:N18) -> -44662207
A19: Cash out: stop-loss premium net of recoveries | C19: =-C12+C13 -> -32562 | D19: =-D12+D13 -> -32887.62 | E19: =-E12+E13 -> -33216.496 | F19: =-F12+F13 -> -33548.661 | G19: =-G12+G13 -> -33884.148 | H19: =-H12+H13 -> -34222.989 | I19: =-I12+I13 -> -34565.219 | J19: =-J12+J13 -> -34910.871 | ... N19: =-N12+N13 -> -36328.393 | O19: =SUM(C19:N19) -> -412967.66
A20: Net provider cash (pre-opex) | C20: =C17+C18+C19 -> 4726699.9 | D20: =D17+D18+D19 -> 4773966.9 | E20: =E17+E18+E19 -> 449715.39 | F20: =F17+F18+F19 -> 476934.9 | G20: =G17+G18+G19 -> 504653.83 | H20: =H17+H18+H19 -> 532879.44 | I20: =I17+I18+I19 -> 561619.1 | J20: =J17+J18+J19 -> 590880.26 | ... N20: =N17+N18+N19 -> 713292.59 | O20: =SUM(C20:N20) -> 15284179
A21: Cumulative cash | C21: =C20 -> 4726699.9 | D21: =C21+D20 -> 9500666.8 | E21: =D21+E20 -> 9950382.2 | F21: =E21+F20 -> 10427317 | G21: =F21+G20 -> 10931971 | H21: =G21+H20 -> 11464850 | I21: =H21+I20 -> 12026469 | J21: =I21+J20 -> 12617350 | K21: =J21+K20 -> 13238020 | ... N21: =M21+N20 -> 15284179 | O21: =N21 -> 15284179
A22: Memo: IBNR / claims payable (provider holds float) | C22: =C11+C18 -> 4371991.2 | D22: =C22+D11+D18 -> 8764980 | E22: =D22+E11+E18 -> 8806957.8 | F22: =E22+F11+F18 -> 8848898.7 | G22: =F22+G11+G18 -> 8890797.8 | H22: =G22+H11+H18 -> 8932649.9 | I22: =H22+I11+I18 -> 8974450 | J22: =I22+J11+J18 -> 9016192.9 | K22: =J22+K11+K18 -> 9057873.1 | ... N22: =M22+N11+N18 -> 9182483.6 | O22: =N22 -> 9182483.6
A24: STRUCTURE 2 - PLAN PAYS & RECONCILES (plan adjudicates; settles vs cap pool)
A25: Cash in: care-management PMPM (operating draw) | C25: ='A. Full Cap'!C6*$B$6 -> 162810 | D25: ='A. Full Cap'!D6*$B$6 -> 164438.1 | E25: ='A. Full Cap'!E6*$B$6 -> 166082.48 | F25: ='A. Full Cap'!F6*$B$6 -> 167743.31 | G25: ='A. Full Cap'!G6*$B$6 -> 169420.74 | H25: ='A. Full Cap'!H6*$B$6 -> 171114.95 | I25: ='A. Full Cap'!I6*$B$6 -> 172826.1 | J25: ='A. Full Cap'!J6*$B$6 -> 174554.36 | ... N25: ='A. Full Cap'!N6*$B$6 -> 181641.96 | O25: =SUM(C25:N25) -> 2064838.3
A26: Cash in: risk-pool settlement received (lag) | C26: 0 | D26: 0 | E26: 0 | F26: 0 | G26: 0 | H26: 0 | I26: 0 | J26: 0 | K26: 0 | L26: 0 | M26: 0 | N26: 0 | O26: =SUM(C26:N26) -> 0
A27: Cash out: claims paid by provider | C27: 0 | D27: 0 | E27: 0 | F27: 0 | G27: 0 | H27: 0 | I27: 0 | J27: 0 | K27: 0 | L27: 0 | M27: 0 | N27: 0 | O27: =SUM(C27:N27) -> 0
A28: Net provider cash (pre-opex) | C28: =C25+C26-C27 -> 162810 | D28: =D25+D26-D27 -> 164438.1 | E28: =E25+E26-E27 -> 166082.48 | F28: =F25+F26-F27 -> 167743.31 | G28: =G25+G26-G27 -> 169420.74 | H28: =H25+H26-H27 -> 171114.95 | I28: =I25+I26-I27 -> 172826.1 | J28: =J25+J26-J27 -> 174554.36 | ... N28: =N25+N26-N27 -> 181641.96 | O28: =SUM(C28:N28) -> 2064838.3
A29: Cumulative cash | C29: =C28 -> 162810 | D29: =C29+D28 -> 327248.1 | E29: =D29+E28 -> 493330.58 | F29: =E29+F28 -> 661073.89 | G29: =F29+G28 -> 830494.63 | H29: =G29+H28 -> 1001609.6 | I29: =H29+I28 -> 1174435.7 | J29: =I29+J28 -> 1348990 | K29: =J29+K28 -> 1525289.9 | ... N29: =M29+N28 -> 2064838.3 | O29: =N29 -> 2064838.3
A30: Memo: settlement receivable/(payable) accrued | C30: =C14-C25 -> 191898.72 | D30: =C30+D14-D25 -> 408438.78 | E30: =D30+E14-E25 -> 650093.83 | F30: =E30+F14-F25 -> 917344.49 | G30: =F30+G14-G25 -> 1210678.5 | H30: =G30+H14-H25 -> 1530590.9 | I30: =H30+I14-I25 -> 1877583.8 | J30: =I30+J14-J25 -> 2252166.9 | K30: =J30+K14-K25 -> 2654857.2 | ... N30: =M30+N14-N25 -> 4036857.2 | O30: =N30 -> 4036857.2
A32: RECONCILIATION - both structures tie to cumulative economic margin
A33: Cumulative economic margin | C33: =C14 -> 354708.72 | D33: =C33+D14 -> 735686.88 | E33: =D33+E14 -> 1143424.4 | F33: =E33+F14 -> 1578418.4 | G33: =F33+G14 -> 2041173.2 | H33: =G33+H14 -> 2532200.5 | I33: =H33+I14 -> 3052019.5 | J33: =I33+J14 -> 3601156.9 | K33: =J33+K14 -> 4180147.1 | ... N33: =M33+N14 -> 6101695.6 | O33: =N33 -> 6101695.6
A34: S1 check: cumulative cash - IBNR payable | C34: =C21-C22 -> 354708.72 | D34: =D21-D22 -> 735686.88 | E34: =E21-E22 -> 1143424.4 | F34: =F21-F22 -> 1578418.4 | G34: =G21-G22 -> 2041173.2 | H34: =H21-H22 -> 2532200.5 | I34: =I21-I22 -> 3052019.5 | J34: =J21-J22 -> 3601156.9 | ... N34: =N21-N22 -> 6101695.6 | O34: =N34 -> 6101695.6
A35: S2 check: cumulative cash + settlement receivable | C35: =C29+C30 -> 354708.72 | D35: =D29+D30 -> 735686.88 | E35: =E29+E30 -> 1143424.4 | F35: =F29+F30 -> 1578418.4 | G35: =G29+G30 -> 2041173.2 | H35: =H29+H30 -> 2532200.5 | I35: =I29+I30 -> 3052019.5 | J35: =J29+J30 -> 3601156.9 | ... N35: =N29+N30 -> 6101695.6 | O35: =N35 -> 6101695.6
A37: WORKING-CAPITAL TAKEAWAY
A38: Structure 1 (delegated): provider receives the full cap up front and pays claims in arrears, so it
A39: sits on a large IBNR float (cash held but owed) - a short-term working-capital positive, but a real
A40: liability that needs reserves, plus claims-adjudication infrastructure (or a delegated TPA).
A41: Structure 2 (plan pays): provider gets only a small steady care-management PMPM for operations; the
A42: economics arrive late as a settlement receivable/(payable). The plan holds the float. Less balance-
A43: sheet risk and no claims shop - but cash depends on the plan's settlement accuracy and timing.
A44: For an early-stage clinic, Structure 2 is the common real-world setup; finance's job is validating the
A45: plan's claims & settlement reports and contesting errors - not running reserves and a claims operation.
